{"index": {"_index": "metaphoem"}}
{"poem_name": "මගේ රට", "poet": "පී.බී.අල්විස් පෙරේරා", "year": "1944", "poem_line": "පෙරදිග ලෝකයේ බබලන මුතු ඇ ටය", "metaphorical_term": "", "source_domain": "", "target_domain": "", "interpretation": ""}
{"index": {"_index": "metaphoem"}}
{"poem_name": "මගේ රට", "poet": "පී.බී.අල්විස් පෙරේරා", "year": "1944", "poem_line": "පණ ඇති මහා සමුදුර පවුරෙන් ව ටය", "metaphorical_term": "සමුදුර පවුරෙන් වටය", "source_domain": "පවුර", "target_domain": "මහා සමුදුර", "interpretation": "ලංකාව වටේ තිබෙන සමුද්‍රය පවුරක් ලෙස සලකා ඇත"}
{"index": {"_index": "metaphoem"}}
{"poem_name": "මගේ රට", "poet": "පී.බී.අල්විස් පෙරේරා", "year": "1944", "poem_line": "හෙල දිවයින මගෙයි මා ඉපදුණ ර ටය", "metaphorical_term": "", "source_domain": "", "target_domain": "", "interpretation": ""}
{"index": {"_index": "metaphoem"}}
{"poem_name": "මගේ රට", "poet": "පී.බී.අල්විස් පෙරේරා", "year": "1944", "poem_line": "ලොව අන් සියලු දිවයින් මේකට ය ටය", "metaphorical_term": "", "source_domain": "", "target_domain": "", "interpretation": ""}
{"index": {"_index": "metaphoem"}}
{"poem_name": "මගේ රට", "poet": "පී.බී.අල්විස් පෙරේරා", "year": "1944", "poem_line": "තෝපා, තඹලගම, මිණිපේ, මින්නේ රි", "metaphorical_term": "", "source_domain": "", "target_domain": "", "interpretation": ""}
{"index": {"_index": "metaphoem"}}
{"poem_name": "මගේ රට", "poet": "පී.බී.අල්විස් පෙරේරා", "year": "1944", "poem_line": "මහ වැව් වලින් දියවැල් ඇදෙමින් බේ රි", "metaphorical_term": "", "source_domain": "", "target_domain": "", "interpretation": ""}
{"index": {"_index": "metaphoem"}}
{"poem_name": "මගේ රට", "poet": "පී.බී.අල්විස් පෙරේරා", "year": "1944", "poem_line": "සරු කරවයි කුඹුරු නිල් පැහැයෙන් මේ රි", "metaphorical_term": "", "source_domain": "", "target_domain": "", "interpretation": ""}
{"index": {"_index": "metaphoem"}}
{"poem_name": "මගේ රට", "poet": "පී.බී.අල්විස් පෙරේරා", "year": "1944", "poem_line": "මගෙ ලක් මෑණියන්දෑ හරි පින් කා රි", "metaphorical_term": "ලක් මෑණියන්දෑ", "source_domain": "ලංකාව", "target_domain": "මෑණියන්", "interpretation": "ලංකාව මෑණියන් ලෙස සලකයි"}
{"index": {"_index": "metaphoem"}}
{"poem_name": "සංසාරේ අපි", "poet": "ජීවිතේ මල් blog", "year": "2010", "poem_line": "ඇසිල්ලක ඇති වී මියෙන සොඳුරු බව", "metaphorical_term": "", "source_domain": "", "target_domain": "", "interpretation": ""}
{"index": {"_index": "metaphoem"}}
{"poem_name": "සංසාරේ අපි", "poet": "ජීවිතේ මල් blog", "year": "2010", "poem_line": "විඳිනු රිසි දඟකාර හිත් පියුම මත,", "metaphorical_term": "හිත් පියුම", "source_domain": "හිත", "target_domain": "පියුම", "interpretation": "සිත පියුමක් මෙන් සියුමැලි බව"}
{"index": {"_index": "metaphoem"}}
{"poem_name": "සංසාරේ අපි", "poet": "ජීවිතේ මල් blog", "year": "2010", "poem_line": "පිපී හැකිලෙන හස රේණුවෙක කෙලවර", "metaphorical_term": "", "source_domain": "", "target_domain": "", "interpretation": ""}
{"index": {"_index": "metaphoem"}}
{"poem_name": "සංසාරේ අපි", "poet": "ජීවිතේ මල් blog", "year": "2010", "poem_line": "රහසක් ඔතා නිදි ගන්වමි මම....", "metaphorical_term": "", "source_domain": "", "target_domain": "", "interpretation": ""}
{"index": {"_index": "metaphoem"}}
{"poem_name": "නාගදීප කාව්‍යය", "poet": "ලුවිස් ද සිල්වා", "year": "1939", "poem_line": "දුම් යතුරෙන් යන සමුදුර යානා", "metaphorical_term": "දුම් යතුරෙන්", "source_domain": "දුම", "target_domain": "යතුර", "interpretation": "නැව් දුම් බලයෙන් යන බව සලකා එය යතුරක් ලෙස භාවිතා කොට ඇත"}
{"index": {"_index": "metaphoem"}}
{"poem_name": "නාගදීප කාව්‍යය", "poet": "ලුවිස් ද සිල්වා", "year": "1939", "poem_line": "පුරවාගත් පසු මහා දන සේනා", "metaphorical_term": "", "source_domain": "", "target_domain": "", "interpretation": ""}
{"index": {"_index": "metaphoem"}}
{"poem_name": "නාගදීප කාව්‍යය", "poet": "ලුවිස් ද සිල්වා", "year": "1939", "poem_line": "දුව ගොස් රල වේගය පසු බානා", "metaphorical_term": "", "source_domain": "", "target_domain": "", "interpretation": ""}
{"index": {"_index": "metaphoem"}}
{"poem_name": "නාගදීප කාව්‍යය", "poet": "ලුවිස් ද සිල්වා", "year": "1939", "poem_line": "සැටියෙන් උපදියි සිතුවිලි නානා", "metaphorical_term": "", "source_domain": "", "target_domain": "", "interpretation": ""}
{"index": {"_index": "metaphoem"}}
{"poem_name": "නාගදීප කාව්‍යය", "poet": "ලුවිස් ද සිල්වා", "year": "1939", "poem_line": "සමහර තැන මග දෙපසෙහි මූදයි", "metaphorical_term": "", "source_domain": "", "target_domain": "", "interpretation": ""}
{"index": {"_index": "metaphoem"}}
{"poem_name": "නාගදීප කාව්‍යය", "poet": "ලුවිස් ද සිල්වා", "year": "1939", "poem_line": "කලපුව මුත් එහි රල වැල යෝදයි", "metaphorical_term": "", "source_domain": "", "target_domain": "", "interpretation": ""}
{"index": {"_index": "metaphoem"}}
{"poem_name": "නාගදීප කාව්‍යය", "poet": "ලුවිස් ද සිල්වා", "year": "1939", "poem_line": "නැග එන ගොස බුදු ගුණ ගී නාදයි", "metaphorical_term": "ගොස බුදු ගුණ ගී නාදයි", "source_domain": "රලින් නැගෙන ඝෝෂාව", "target_domain": "බුදු ගුණ ගී", "interpretation": "ඝෝෂාවක් වුවත් බුදු ගුණ ගීයක් සේ කන්කළු බව"}
{"index": {"_index": "metaphoem"}}
{"poem_name": "නාගදීප කාව්‍යය", "poet": "ලුවිස් ද සිල්වා", "year": "1939", "poem_line": "හැම මොහොතේම ගමනට සිත පාදයි", "metaphorical_term": "", "source_domain": "", "target_domain": "", "interpretation": ""}
{"index": {"_index": "metaphoem"}}
{"poem_name": "වදන් කවි පොත", "poet": "අත්තරගම බණ්ඩාර රාජගුරු", "year": "", "poem_line": "මූදු අසල් බඩ සිටිනා එ නුවරෙකී", "metaphorical_term": "", "source_domain": "", "target_domain": "", "interpretation": ""}
{"index": {"_index": "metaphoem"}}
{"poem_name": "වදන් කවි පොත", "poet": "අත්තරගම බණ්ඩාර රාජගුරු", "year": "", "poem_line": "ඉස බැඳි ඔටුන්නෙන් සැදුණේ රජවරුවෙකී", "metaphorical_term": "", "source_domain": "", "target_domain": "", "interpretation": ""}
{"index": {"_index": "metaphoem"}}
{"poem_name": "වදන් කවි පොත", "poet": "අත්තරගම බණ්ඩාර රාජගුරු", "year": "", "poem_line": "දෙපා පියුම් පෙති සුරතට රනෙන් වැකී", "metaphorical_term": "දෙපා පියුම් පෙති", "source_domain": "ඩෙපා", "target_domain": "පියුම් පෙති", "interpretation": "පාද නෙළුම් මල් තරම් සියුමැලි බව"}
{"index": {"_index": "metaphoem"}}
{"poem_name": "වදන් කවි පොත", "poet": "අත්තරගම බණ්ඩාර රාජගුරු", "year": "", "poem_line": "ඇඳින ගොසින් වඳු දෙවුරජ මේ ලෙස කී", "metaphorical_term": "", "source_domain": "", "target_domain": "", "interpretation": ""}
{"index": {"_index": "metaphoem"}}
{"poem_name": "පැල් කවි", "poet": "ජන කවි", "year": "", "poem_line": "දුම්බර කෙතට වැට බැදලා රැකුම් බැලුම්", "metaphorical_term": "", "source_domain": "", "target_domain": "", "interpretation": ""}
{"index": {"_index": "metaphoem"}}
{"poem_name": "පැල් කවි", "poet": "ජන කවි", "year": "", "poem_line": "මහවැලි ගඟේ දිය ගලලා කෙතට ගිලුම්", "metaphorical_term": "", "source_domain": "", "target_domain": "", "interpretation": ""}
{"index": {"_index": "metaphoem"}}
{"poem_name": "පැල් කවි", "poet": "ජන කවි", "year": "", "poem_line": "පෙම්බර ලියන් කර ඔසවා බලන බැලුම්", "metaphorical_term": "", "source_domain": "", "target_domain": "", "interpretation": ""}
{"index": {"_index": "metaphoem"}}
{"poem_name": "පැල් කවි", "poet": "ජන කවි", "year": "", "poem_line": "තුම්පත් රටාවකි දුම්බර කෙතේ නෙලුම්", "metaphorical_term": "තුම්පත් රටාවකි දුම්බර කෙතේ නෙළුම්", "source_domain": "දුම්බර කෙතේ නෙළුම්", "target_domain": "තුම්පත් රටාව", "interpretation": "ගොයම් කපන විට රටාවකට කපන බැවින් එහි අලංකාර බව"}
{"index": {"_index": "metaphoem"}}
{"poem_name": "පැල් කවි", "poet": "ජන කවි", "year": "", "poem_line": "කන්ද උඩින් එන කිකිළිය ගෝමරියේ", "metaphorical_term": "", "source_domain": "", "target_domain": "", "interpretation": ""}
{"index": {"_index": "metaphoem"}}
{"poem_name": "පැල් කවි", "poet": "ජන කවි", "year": "", "poem_line": "නළල් වටින් එන දාඩිය මුතු සැටියේ", "metaphorical_term": "දාඩිය මුතු", "source_domain": "දාඩිය", "target_domain": "මුතු", "interpretation": "මහන්සි වී වැඩ කරන විට නැගෙන දහඩිය මුතු වගේය"}
{"index": {"_index": "metaphoem"}}
{"poem_name": "පැල් කවි", "poet": "ජන කවි", "year": "", "poem_line": "අත පා මුදු පය පා මුදු වයිරොඩියේ", "metaphorical_term": "", "source_domain": "", "target_domain": "", "interpretation": ""}
{"index": {"_index": "metaphoem"}}
{"poem_name": "පැල් කවි", "poet": "ජන කවි", "year": "", "poem_line": "මට පිටුපා ගෙට යනවද සුරතලියේ", "metaphorical_term": "", "source_domain": "", "target_domain": "", "interpretation": ""}
{"index": {"_index": "metaphoem"}}
{"poem_name": "කුරක්කන් කවි", "poet": "ජන කවි", "year": "", "poem_line": "කුරක්කන් කපන වාරෙත් ආපි ළමා", "metaphorical_term": "", "source_domain": "", "target_domain": "", "interpretation": ""}
{"index": {"_index": "metaphoem"}}
{"poem_name": "කුරක්කන් කවි", "poet": "ජන කවි", "year": "", "poem_line": "නරක්කන් අව්ව මූණට තදයි ළමා", "metaphorical_term": "", "source_domain": "", "target_domain": "", "interpretation": ""}
{"index": {"_index": "metaphoem"}}
{"poem_name": "කුරක්කන් කවි", "poet": "ජන කවි", "year": "", "poem_line": "නළල් වටින් එන දාඩිය මුතු සේමා", "metaphorical_term": "", "source_domain": "", "target_domain": "", "interpretation": ""}
{"index": {"_index": "metaphoem"}}
{"poem_name": "කුරක්කන් කවි", "poet": "ජන කවි", "year": "", "poem_line": "මා දෙස නොබලන්ට නුඹෙ අත කැපෙයි ළමා", "metaphorical_term": "", "source_domain": "", "target_domain": "", "interpretation": ""}
{"index": {"_index": "metaphoem"}}
{"poem_name": "බඹර කවි", "poet": "ජන කවි", "year": "", "poem_line": "උඩ මාලේ මල් වැසි වැස්සක් යනවා", "metaphorical_term": "", "source_domain": "", "target_domain": "", "interpretation": ""}
{"index": {"_index": "metaphoem"}}
{"poem_name": "බඹර කවි", "poet": "ජන කවි", "year": "", "poem_line": "බිම මාලේ මල් වැසි වැස්සක් යනවා", "metaphorical_term": "", "source_domain": "", "target_domain": "", "interpretation": ""}
{"index": {"_index": "metaphoem"}}
{"poem_name": "බඹර කවි", "poet": "ජන කවි", "year": "", "poem_line": "ළිප ළියගල් තැන වෙන්වුවොත් යනවා", "metaphorical_term": "", "source_domain": "", "target_domain": "", "interpretation": ""}
{"index": {"_index": "metaphoem"}}
{"poem_name": "බඹර කවි", "poet": "ජන කවි", "year": "", "poem_line": "නා ගහ බඹරෙ කැපුමට දෙන්නම යනවා", "metaphorical_term": "", "source_domain": "", "target_domain": "", "interpretation": ""}
{"index": {"_index": "metaphoem"}}
{"poem_name": "බඹර කවි", "poet": "ජන කවි", "year": "", "poem_line": "බැද්ද හැම තැනම මොර මල් සුදු එළියා", "metaphorical_term": "මොර මල් සුදු එලිය", "source_domain": "මොර මල්", "target_domain": "සුදු එලිය", "interpretation": "සුදු පාට මොරමල් නිසා කැලය ආලෝක මත් වී ඇති බව"}
{"index": {"_index": "metaphoem"}}
{"poem_name": "බඹර කවි", "poet": "ජන කවි", "year": "", "poem_line": "සද්ද කර බඹරු රොන් ගෙන යති එළියා", "metaphorical_term": "", "source_domain": "", "target_domain": "", "interpretation": ""}
{"index": {"_index": "metaphoem"}}
{"poem_name": "බඹර කවි", "poet": "ජන කවි", "year": "", "poem_line": "පණික්කිවරු ඇවිත් උන් හට සිත් පිරියා", "metaphorical_term": "", "source_domain": "", "target_domain": "", "interpretation": ""}
{"index": {"_index": "metaphoem"}}
{"poem_name": "බඹර කවි", "poet": "ජන කවි", "year": "", "poem_line": "කවර කලක දක්වුද අපි ඔය සැටියා", "metaphorical_term": "", "source_domain": "", "target_domain": "", "interpretation": ""}
{"index": {"_index": "metaphoem"}}
{"poem_name": "පාරු කවි", "poet": "ජන කවි", "year": "", "poem_line": "මස්සිනාගෙ මඟුලට මම රුහුණු ගියේ", "metaphorical_term": "", "source_domain": "", "target_domain": "", "interpretation": ""}
{"index": {"_index": "metaphoem"}}
{"poem_name": "පාරු කවි", "poet": "ජන කවි", "year": "", "poem_line": "ලස්සන ගමන් බඩු පටවා එන්ට ගියේ", "metaphorical_term": "", "source_domain": "", "target_domain": "", "interpretation": ""}
{"index": {"_index": "metaphoem"}}
{"poem_name": "පාරු කවි", "poet": "ජන කවි", "year": "", "poem_line": "පස්ස බලන කොට අගුලක් ගිලී ගියේ", "metaphorical_term": "", "source_domain": "", "target_domain": "", "interpretation": ""}
{"index": {"_index": "metaphoem"}}
{"poem_name": "පාරු කවි", "poet": "ජන කවි", "year": "", "poem_line": "රත්තරන් ලියකි තෙලිකඩ ගඟේ ගියේ", "metaphorical_term": "රත්තරන් ලියකි", "source_domain": "ලිය", "target_domain": "රත්තරන්", "interpretation": "ගඟේ ගිය කාන්තාව ඉතා රූමත් බව"}
{"index": {"_index": "metaphoem"}}
{"poem_name": "පාරු කවි", "poet": "ජන කවි", "year": "", "poem_line": "සස්සඳ සස්සඳ දිය මතුපිට තියේ මල", "metaphorical_term": "", "source_domain": "", "target_domain": "", "interpretation": ""}
{"index": {"_index": "metaphoem"}}
{"poem_name": "පාරු කවි", "poet": "ජන කවි", "year": "", "poem_line": "සස්සඳ සස්සඳ දිය පල්ලේ තියේ අල", "metaphorical_term": "", "source_domain": "", "target_domain": "", "interpretation": ""}
{"index": {"_index": "metaphoem"}}
{"poem_name": "පාරු කවි", "poet": "ජන කවි", "year": "", "poem_line": "වැස්සට පිනි බබා මෝරන කැකුළු මල", "metaphorical_term": "", "source_domain": "", "target_domain": "", "interpretation": ""}
{"index": {"_index": "metaphoem"}}
{"poem_name": "පාරු කවි", "poet": "ජන කවි", "year": "", "poem_line": "මස්ටකයින්ට මුතු කුඩයකි නෙළුම් මල", "metaphorical_term": "මස්ටකයින්ට මුතු කුඩයකි නෙළුම්මල", "source_domain": "නෙළුම්මල", "target_domain": "මුතුකුඩය", "interpretation": "මත්ස්‍යයින් වැස්ස පටන් ගත් විට නෙළුම් මල් ආසන්නයට පැමිණෙයි"}
{"index": {"_index": "metaphoem"}}
{"poem_name": "ගොයම් කවි", "poet": "ජන කවි", "year": "", "poem_line": "කුඹුරු පුබුදු මල් සුවඳයි හැම විට", "metaphorical_term": "", "source_domain": "", "target_domain": "", "interpretation": ""}
{"index": {"_index": "metaphoem"}}
{"poem_name": "ගොයම් කවි", "poet": "ජන කවි", "year": "", "poem_line": "බඹරු ඇවිත් රොන් ගෙනයති උදයට", "metaphorical_term": "", "source_domain": "", "target_domain": "", "interpretation": ""}
{"index": {"_index": "metaphoem"}}
{"poem_name": "ගොයම් කවි", "poet": "ජන කවි", "year": "", "poem_line": "මදුරු කිඳුරු නද හැඩවෙති වාතෙට", "metaphorical_term": "මදුරු කිඳුරු නද", "source_domain": "මදුරු නද", "target_domain": "කිඳුරු නද", "interpretation": "මදුරු නද කරදරයක් වුවත් එය සුන්දර කිඳුරු නාදයක් සේ දැක ඇත"}
{"index": {"_index": "metaphoem"}}
{"poem_name": "ගොයම් කවි", "poet": "ජන කවි", "year": "", "poem_line": "නැඹුරු වෙලා ඉති ගෝමර තරමට", "metaphorical_term": "", "source_domain": "", "target_domain": "", "interpretation": ""}
{"index": {"_index": "metaphoem"}}
{"poem_name": "ගොයම් කවි", "poet": "ජන කවි", "year": "", "poem_line": "ගොයම් කපා ඉවර වුණා", "metaphorical_term": "", "source_domain": "", "target_domain": "", "interpretation": ""}
{"index": {"_index": "metaphoem"}}
{"poem_name": "ගොයම් කවි", "poet": "ජන කවි", "year": "", "poem_line": "ඉර දෙයියෝ පිහිට වුණා", "metaphorical_term": "ඉර දෙයියෝ", "source_domain": "ඉර", "target_domain": "දෙයියෝ", "interpretation": "වැස්ස නැතිව දිනය පුරා ආලෝකය ලැබුනු නිසා ඉර දෙවියන් සේ පිහිට වී ඇත"}
{"index": {"_index": "metaphoem"}}
{"poem_name": "ගොයම් කවි", "poet": "ජන කවි", "year": "", "poem_line": "ගොවි රාළට සෙතක් වුණා", "metaphorical_term": "", "source_domain": "", "target_domain": "", "interpretation": ""}
{"index": {"_index": "metaphoem"}}
{"poem_name": "ගොයම් කවි", "poet": "ජන කවි", "year": "", "poem_line": "අපේ සිතත් සතුටු වුණා", "metaphorical_term": "", "source_domain": "", "target_domain": "", "interpretation": ""}
{"index": {"_index": "metaphoem"}}
{"poem_name": "උගත්කම", "poet": "කේයස් (සාගර පලන්සූරිය)", "year": "1940", "poem_line": "එළු සකු මගද පොත් කට පාඩමට දනී", "metaphorical_term": "", "source_domain": "", "target_domain": "", "interpretation": ""}
{"index": {"_index": "metaphoem"}}
{"poem_name": "උගත්කම", "poet": "කේයස් (සාගර පලන්සූරිය)", "year": "1940", "poem_line": "මිනිහා පණපිටින් යන පොත් ගුලක් වැනී", "metaphorical_term": "", "source_domain": "", "target_domain": "", "interpretation": ""}
{"index": {"_index": "metaphoem"}}
{"poem_name": "උගත්කම", "poet": "කේයස් (සාගර පලන්සූරිය)", "year": "1940", "poem_line": "වැගිරෙන විලස සාහිත රස අමර පැනී", "metaphorical_term": "සාහිත රස අමර පැනී", "source_domain": "සාහිත්‍යය", "target_domain": "අමර පැනි", "interpretation": "සාහිත්‍යයේ සුන්දරත්වය දෙව්ලොව තිබෙන අමර පැනි ලෙස අර්ථ ගන්වා ඇත"}
{"index": {"_index": "metaphoem"}}
{"poem_name": "උගත්කම", "poet": "කේයස් (සාගර පලන්සූරිය)", "year": "1940", "poem_line": "පොතක් ලියන්නට සිතිවිලි පහල වුණී", "metaphorical_term": "", "source_domain": "", "target_domain": "", "interpretation": ""}
{"index": {"_index": "metaphoem"}}
{"poem_name": "වලස් දඩයම", "poet": " විමලරත්න කුමාරගම", "year": "1946", "poem_line": "පලු ගහ අවට නැගි මැහි මදුරු නැළවිලි", "metaphorical_term": "", "source_domain": "", "target_domain": "", "interpretation": ""}
{"index": {"_index": "metaphoem"}}
{"poem_name": "වලස් දඩයම", "poet": " විමලරත්න කුමාරගම", "year": "1946", "poem_line": "තරු මල් වලා ගුලි නිල් ගුවන සැරසිලි", "metaphorical_term": "තරු මල්", "source_domain": "තරු", "target_domain": "මල්", "interpretation": "නිල් අහසේ මල් පිපී ඇති අයුරින් තරු පායා ඇති බව"}
{"index": {"_index": "metaphoem"}}
{"poem_name": "වලස් දඩයම", "poet": " විමලරත්න කුමාරගම", "year": "1946", "poem_line": "වැව් දිය ඇල් මැරී මසු අතර කැලඹිලි", "metaphorical_term": "", "source_domain": "", "target_domain": "", "interpretation": ""}
{"index": {"_index": "metaphoem"}}
{"poem_name": "වලස් දඩයම", "poet": " විමලරත්න කුමාරගම", "year": "1946", "poem_line": "බැලු හැම තැන ම මතු ‍වුණු අමුතු සෙවණැලි", "metaphorical_term": "", "source_domain": "", "target_domain": "", "interpretation": ""}
{"index": {"_index": "metaphoem"}}
{"poem_name": "අඳුර අපේ දුක නිවාවී", "poet": "ගුණදාස අමරසේකර", "year": "1952", "poem_line": "ගෙදර ගිහින් ඇළ ගාවින් හොඳ තණකොළ ටිකක් උඹට", "metaphorical_term": "", "source_domain": "", "target_domain": "", "interpretation": ""}
{"index": {"_index": "metaphoem"}}
{"poem_name": "අඳුර අපේ දුක නිවාවී", "poet": "ගුණදාස අමරසේකර", "year": "1952", "poem_line": "තලු ගහ ගහ බඩ පිරෙන්න ගෙනැත් දාන්නම්    කන්නට", "metaphorical_term": "", "source_domain": "", "target_domain": "", "interpretation": ""}
{"index": {"_index": "metaphoem"}}
{"poem_name": "අඳුර අපේ දුක නිවාවී", "poet": "ගුණදාස අමරසේකර", "year": "1952", "poem_line": "දෙයියො තමයි අඳුර දුන්නේ අපෙ ඇඟපත ගිනි නිවන්ට", "metaphorical_term": "", "source_domain": "", "target_domain": "", "interpretation": ""}
{"index": {"_index": "metaphoem"}}
{"poem_name": "අඳුර අපේ දුක නිවාවී", "poet": "ගුණදාස අමරසේකර", "year": "1952", "poem_line": "හනික යමන් ගාල් වෙලා අඳුරු රෙද්ද පෙරව        ගන්ට", "metaphorical_term": "අඳුරු රෙද්ද", "source_domain": "අඳුරු", "target_domain": "රෙද්ද", "interpretation": "අන්ධකාරයේ සිටින විට කිසිත් නොපෙනෙන බව රෙද්දක් පෙරවූව ලෙසට"}
{"index": {"_index": "metaphoem"}}
{"poem_name": "ගංඟාවේ ගීතය", "poet": "එච්.එම් කුඩලිගම", "year": "1940", "poem_line": "සැඟවෙමි එබෙමි නිසසල වෙමි සසල     වෙමි", "metaphorical_term": "", "source_domain": "", "target_domain": "", "interpretation": ""}
{"index": {"_index": "metaphoem"}}
{"poem_name": "ගංඟාවේ ගීතය", "poet": "එච්.එම් කුඩලිගම", "year": "1940", "poem_line": "ඇඹරෙමි එහෙත් පසු නොබසිමි   නොනවතිමි", "metaphorical_term": "", "source_domain": "", "target_domain": "", "interpretation": ""}
{"index": {"_index": "metaphoem"}}
{"poem_name": "ගංඟාවේ ගීතය", "poet": "එච්.එම් කුඩලිගම", "year": "1940", "poem_line": "කවදා කොතනදී හෝ මහ මුහුද හිමී", "metaphorical_term": "මහ මුහුද හිමී", "source_domain": "මහ මුහුද", "target_domain": "හිමි", "interpretation": "ස්වාමියා සොයා යන කාන්තාවක් මෙන් නදිය මුහුද සොයා යයි"}
{"index": {"_index": "metaphoem"}}
{"poem_name": "ගංඟාවේ ගීතය", "poet": "එච්.එම් කුඩලිගම", "year": "1940", "poem_line": "හමුවුණු කෙනෙහි මා සතු බර ඔබට දෙමි", "metaphorical_term": "", "source_domain": "", "target_domain": "", "interpretation": ""}
{"index": {"_index": "metaphoem"}}
{"poem_name": "ගංඟාවේ ගීතය", "poet": "එච්.එම් කුඩලිගම", "year": "1940", "poem_line": "හිරිමල් සිනා රැළි පෙණ පිඬු මිහිරිතම", "metaphorical_term": "හිරිමල් සිනාරැලි පෙනපිඬු", "source_domain": "පෙනපිඬු", "target_domain": "හිරිමල් සිනාරැලි", "interpretation": "ගල්පර වල ගටී ඇතිවන පෙනපිඬු සිනාරැල් මෙන් සුන්දරය"}
{"index": {"_index": "metaphoem"}}
{"poem_name": "ගංඟාවේ ගීතය", "poet": "එච්.එම් කුඩලිගම", "year": "1940", "poem_line": "ගල් පරවලම හැපි හැපි බිහිකරමි  මම", "metaphorical_term": "", "source_domain": "", "target_domain": "", "interpretation": ""}
{"index": {"_index": "metaphoem"}}
{"poem_name": "ගංඟාවේ ගීතය", "poet": "එච්.එම් කුඩලිගම", "year": "1940", "poem_line": "සම තැනිතලාවල හමුවෙයි අලසකම", "metaphorical_term": "", "source_domain": "", "target_domain": "", "interpretation": ""}
{"index": {"_index": "metaphoem"}}
{"poem_name": "ගංඟාවේ ගීතය", "poet": "එච්.එම් කුඩලිගම", "year": "1940", "poem_line": "නිරසයි අතරමග අවහිර නොදුටු බිම", "metaphorical_term": "", "source_domain": "", "target_domain": "", "interpretation": ""}
{"index": {"_index": "metaphoem"}}
{"poem_name": "නිදහස් උදානය", "poet": "සුගුණපාල සමරසේකර", "year": "1980", "poem_line": "විදෙසික පීඩන ගිම්              උනවා", "metaphorical_term": "", "source_domain": "", "target_domain": "", "interpretation": ""}
{"index": {"_index": "metaphoem"}}
{"poem_name": "නිදහස් උදානය", "poet": "සුගුණපාල සමරසේකර", "year": "1980", "poem_line": "නිදහස් මඳනල රැළි            දෙනවා", "metaphorical_term": "නිදහස් මද්නල", "source_domain": "නිදහස", "target_domain": "මදනල", "interpretation": "මදනල ඇඟට සිසිලසක් ගෙනදෙයි. නිදහස එමෙන්ම අවට සුවයක් සාදයි"}
{"index": {"_index": "metaphoem"}}
{"poem_name": "නිදහස් උදානය", "poet": "සුගුණපාල සමරසේකර", "year": "1980", "poem_line": "ලක්මව රන්කොඩි ලෙළ      වනවා", "metaphorical_term": "", "source_domain": "", "target_domain": "", "interpretation": ""}
{"index": {"_index": "metaphoem"}}
{"poem_name": "නිදහස් උදානය", "poet": "සුගුණපාල සමරසේකර", "year": "1980", "poem_line": "මෙන් සිරිමා බෝ දලු           ලනවා", "metaphorical_term": "", "source_domain": "", "target_domain": "", "interpretation": ""}
{"index": {"_index": "metaphoem"}}
{"poem_name": "නිදහස් උදානය", "poet": "සුගුණපාල සමරසේකර", "year": "1980", "poem_line": "පෙණකැටි මුතුපට ඉහළට      නංගා", "metaphorical_term": "පෙණකැටි මුතුපට", "source_domain": "පෙණකැටි", "target_domain": "පුතුපට", "interpretation": "පුහුදු රලින් විසිරෙන පෙනකැට ඉහලට විසිරෙන්නේ මුතුපටක් වගේ"}
{"index": {"_index": "metaphoem"}}
{"poem_name": "නිදහස් උදානය", "poet": "සුගුණපාල සමරසේකර", "year": "1980", "poem_line": "රළ පෙළ තරඟෙට වෙරළට නැංගා", "metaphorical_term": "", "source_domain": "", "target_domain": "", "interpretation": ""}
{"index": {"_index": "metaphoem"}}
{"poem_name": "නිදහස් උදානය", "poet": "සුගුණපාල සමරසේකර", "year": "1980", "poem_line": "පළකොට නිදහස සතුටු        තරංගා", "metaphorical_term": "නිදහස සතුටු තරංගා", "source_domain": "නිදහස", "target_domain": "සතුටු තරංගා", "interpretation": "නිදහස දිය තරංග ලෙස ගංගාවල් දිගේ ගලන බව"}
{"index": {"_index": "metaphoem"}}
{"poem_name": "නිදහස් උදානය", "poet": "සුගුණපාල සමරසේකර", "year": "1980", "poem_line": "හෙමිහිට බැසයෙති ගිං කළු    ගංඟා", "metaphorical_term": "", "source_domain": "", "target_domain": "", "interpretation": ""}
{"index": {"_index": "metaphoem"}}
{"poem_name": "නිදහස් උදානය", "poet": "සුගුණපාල සමරසේකර", "year": "1980", "poem_line": "නිදහස පිළිබඳ දිමුතු       ජයන්තිය", "metaphorical_term": "", "source_domain": "", "target_domain": "", "interpretation": ""}
{"index": {"_index": "metaphoem"}}
{"poem_name": "නිදහස් උදානය", "poet": "සුගුණපාල සමරසේකර", "year": "1980", "poem_line": "සළකන ඔබ අද හරි පින්   වන්තිය", "metaphorical_term": "", "source_domain": "", "target_domain": "", "interpretation": ""}
{"index": {"_index": "metaphoem"}}
{"poem_name": "නිදහස් උදානය", "poet": "සුගුණපාල සමරසේකර", "year": "1980", "poem_line": "කිය කිය දිවගෙන සිඳුරළ  පන්තිය", "metaphorical_term": "", "source_domain": "", "target_domain": "", "interpretation": ""}
{"index": {"_index": "metaphoem"}}
{"poem_name": "නිදහස් උදානය", "poet": "සුගුණපාල සමරසේකර", "year": "1980", "poem_line": "සිඹගති සිරිලක් ආදර        වන්තිය", "metaphorical_term": "සිරිලක් ආදරවන්තිය", "source_domain": "සිරිලක", "target_domain": "ආදර වන්තිය", "interpretation": "රටට ඉතාමත් ආදරය කරන බව මෙයින් දැක්වේ"}
{"index": {"_index": "metaphoem"}}
{"poem_name": "උතුරෙන්", "poet": "සාගර පළන්සූරිය", "year": "1940", "poem_line": "ගෙන එයි මිහිර ගී මදනල  හමන                විට", "metaphorical_term": "ගී මදනල", "source_domain": "මදනල ල්", "target_domain": "ගී", "interpretation": "සෙමෙන් හමන සුළඟ ගීතයක් මෙන් ඇසෙයි"}
{"index": {"_index": "metaphoem"}}
{"poem_name": "උතුරෙන්", "poet": "සාගර පළන්සූරිය", "year": "1940", "poem_line": "වැටහෙයි නොවැටහුණු සැඟවුණු කරුණු    මට", "metaphorical_term": "", "source_domain": "", "target_domain": "", "interpretation": ""}
{"index": {"_index": "metaphoem"}}
{"poem_name": "උතුරෙන්", "poet": "සාගර පළන්සූරිය", "year": "1940", "poem_line": "නිල් පැහැයක් නැතත් මේ වැලි පොළව      පිට", "metaphorical_term": "", "source_domain": "", "target_domain": "", "interpretation": ""}
{"index": {"_index": "metaphoem"}}
{"poem_name": "උතුරෙන්", "poet": "සාගර පළන්සූරිය", "year": "1940", "poem_line": "උදයට පෙනේ බොල් පිනිබිඳු පබළු           ඇට", "metaphorical_term": "පිනිබිඳු පබළු ඇට", "source_domain": "පිනිබිඳු", "target_domain": "පබළු ඇට", "interpretation": "උදය කාලයේ වැටී තිබෙන පිනිබිඳු වල හිරුරැස් වැටී බබලන විට වෛවර්ණ පබළු මෙනි"}
{"index": {"_index": "metaphoem"}}
{"poem_name": "උතුරෙන්", "poet": "සාගර පළන්සූරිය", "year": "1940", "poem_line": "බැඳ ඇති විළංගුව පා මිණිසළඹ              කොට", "metaphorical_term": "විලංගුව පා මිණිසළඹ", "source_domain": "විලංගුව", "target_domain": "මිණිසළඹ", "interpretation": "බාධකයක් ඒ ලෙසම නොසිතා ආශිර්වාදයක් ලෙස සලකා ඇත"}
{"index": {"_index": "metaphoem"}}
{"poem_name": "උතුරෙන්", "poet": "සාගර පළන්සූරිය", "year": "1940", "poem_line": "සලකා වැටෙන එය බැන්දහු ඉදිරි                පිට", "metaphorical_term": "", "source_domain": "", "target_domain": "", "interpretation": ""}
{"index": {"_index": "metaphoem"}}
{"poem_name": "උතුරෙන්", "poet": "සාගර පළන්සූරිය", "year": "1940", "poem_line": "මිනිසුන් දකුණෙ මෙන් උතුරෙත් පෙනෙන විට", "metaphorical_term": "", "source_domain": "", "target_domain": "", "interpretation": ""}
{"index": {"_index": "metaphoem"}}
{"poem_name": "උතුරෙන්", "poet": "සාගර පළන්සූරිය", "year": "1940", "poem_line": "සිහියෙන් තුරන් වෙයි හෙට යන දවස         මට", "metaphorical_term": "", "source_domain": "", "target_domain": "", "interpretation": ""}
{"index": {"_index": "metaphoem"}}
{"poem_name": "ටාසන් මළා", "poet": "විමලරත්න කුමාරගම", "year": "1951", "poem_line": "සන් දෙන වෙණක් සේ සිහිපස හඳ     පානේ", "metaphorical_term": "", "source_domain": "", "target_domain": "", "interpretation": ""}
{"index": {"_index": "metaphoem"}}
{"poem_name": "ටාසන් මළා", "poet": "විමලරත්න කුමාරගම", "year": "1951", "poem_line": "දුන් නෙහි  උඹත් මට හුදු සෙනෙහස   දානේ", "metaphorical_term": "සෙනෙහස දානේ", "source_domain": "සෙනෙහස", "target_domain": "දානේ", "interpretation": "සෙනෙහස ලබා දී ඇත්තේ ආපසු බලාපොරොත්තුවෙන් නොවෙයි දානයක් දුන්නාක් මෙනි"}
{"index": {"_index": "metaphoem"}}
{"poem_name": "ටාසන් මළා", "poet": "විමලරත්න කුමාරගම", "year": "1951", "poem_line": "දැන් මට දැනෙන්නේ හැබැහින් හෝ   සීනේ", "metaphorical_term": "", "source_domain": "", "target_domain": "", "interpretation": ""}
{"index": {"_index": "metaphoem"}}
{"poem_name": "ටාසන් මළා", "poet": "විමලරත්න කුමාරගම", "year": "1951", "poem_line": "රන් කිරියා මල් සුවඳයි උඹෙ              මූනේ", "metaphorical_term": "", "source_domain": "", "target_domain": "", "interpretation": ""}
{"index": {"_index": "metaphoem"}}
{"poem_name": "ආලින්දය", "poet": "එරික් ඉලයප්ආරච්චි", "year": "1988", "poem_line": "පාන ළඟ වැඳ වැටෙන අම්මාගෙ මුව මඬල", "metaphorical_term": "මුව මඩල", "source_domain": "මුහුණ", "target_domain": "මණ්ඩලය", "interpretation": "අම්මාගේ මුහුණ දිලිසෙමින් තියෙන බව කියවේ."}
{"index": {"_index": "metaphoem"}}
{"poem_name": "ආලින්දය", "poet": "එරික් ඉලයප්ආරච්චි", "year": "1988", "poem_line": "පසුපසින් පෙළ ගැසෙන නැඟෙණියන්ගේ පිළිම", "metaphorical_term": "", "source_domain": "", "target_domain": "", "interpretation": ""}
{"index": {"_index": "metaphoem"}}
{"poem_name": "ආලින්දය", "poet": "එරික් ඉලයප්ආරච්චි", "year": "1988", "poem_line": "සැඳෑ එළියේ ඇඳෙන සංසාර සෙවණැල්ල", "metaphorical_term": "සංසාර සෙවනැල්ල", "source_domain": "සංසාරය", "target_domain": "සෙවනැල්ල", "interpretation": "සෙවනැල්ල අප හැර නොයන්නා වාගේ සංසාරයත් අප හැර නොයයි"}
{"index": {"_index": "metaphoem"}}
{"poem_name": "ආලින්දය", "poet": "එරික් ඉලයප්ආරච්චි", "year": "1988", "poem_line": "බලා සිටියෙමි  තනි ව ලීස්තර වැට මැදින්", "metaphorical_term": "", "source_domain": "", "target_domain": "", "interpretation": ""}
{"index": {"_index": "metaphoem"}}
{"poem_name": "අයියනායක", "poet": "විමලරත්න කුමාරගම", "year": "1946", "poem_line": "සාගත වසංගත හා එන නියඟ                    වලින්", "metaphorical_term": "", "source_domain": "", "target_domain": "", "interpretation": ""}
{"index": {"_index": "metaphoem"}}
{"poem_name": "අයියනායක", "poet": "විමලරත්න කුමාරගම", "year": "1946", "poem_line": "සහනය පතා වන දෙවියන් ළඟට           කෙළින්", "metaphorical_term": "", "source_domain": "", "target_domain": "", "interpretation": ""}
{"index": {"_index": "metaphoem"}}
{"poem_name": "අයියනායක", "poet": "විමලරත්න කුමාරගම", "year": "1946", "poem_line": "එන මේ පිරිස සැරසීමට නුවණ                 මලින්", "metaphorical_term": "නුවණ මලින්", "source_domain": "නුවණ", "target_domain": "මල්", "interpretation": "නුවණ නැතිව සිටින අයට නුවණ ලබාදීම අදහස් කරයි"}
{"index": {"_index": "metaphoem"}}
{"poem_name": "අයියනායක", "poet": "විමලරත්න කුමාරගම", "year": "1946", "poem_line": "පෙළෙඹෙන අයට අනුකම්පා කරමි          මුලින්", "metaphorical_term": "", "source_domain": "", "target_domain": "", "interpretation": ""}
{"index": {"_index": "metaphoem"}}
{"poem_name": "කවියා", "poet": "ආර්.සරණසේකර", "year": "", "poem_line": "බසේ කිලිටිකම නැණ සිලිලින්                    දොවනා", "metaphorical_term": "නැණු සිලිලින්", "source_domain": "නුවන", "target_domain": "සිලිල", "interpretation": "ඥානය නැමැති වතුරින් බසේ කිලිටිකම සෝදා හැරිය හැකි බව"}
{"index": {"_index": "metaphoem"}}
{"poem_name": "කවියා", "poet": "ආර්.සරණසේකර", "year": "", "poem_line": "රැසේ සියල්ලන් හට තව පණ                     පොවනා", "metaphorical_term": "", "source_domain": "", "target_domain": "", "interpretation": ""}
{"index": {"_index": "metaphoem"}}
{"poem_name": "කවියා", "poet": "ආර්.සරණසේකර", "year": "", "poem_line": "දෙසේ අමුතු මිහිරක් සතුටක්                          වවනා", "metaphorical_term": "", "source_domain": "", "target_domain": "", "interpretation": ""}
{"index": {"_index": "metaphoem"}}
{"poem_name": "කවියා", "poet": "ආර්.සරණසේකර", "year": "", "poem_line": "කෙසේ කියැහැකිද කිවිඳුගෙ අගය                   වනා", "metaphorical_term": "", "source_domain": "", "target_domain": "", "interpretation": ""}
{"index": {"_index": "metaphoem"}}
{"poem_name": "කවියා", "poet": "ආර්.සරණසේකර", "year": "", "poem_line": "සියසත තුළෙහි ඉසි කෝ මද මාන                    නහා", "metaphorical_term": "", "source_domain": "", "target_domain": "", "interpretation": ""}
{"index": {"_index": "metaphoem"}}
{"poem_name": "කවියා", "poet": "ආර්.සරණසේකර", "year": "", "poem_line": "සුනිසිත නැණින් කරුණා මෙත් මිහිර                බහා", "metaphorical_term": "", "source_domain": "", "target_domain": "", "interpretation": ""}
{"index": {"_index": "metaphoem"}}
{"poem_name": "කවියා", "poet": "ආර්.සරණසේකර", "year": "", "poem_line": "විලසිත සුවඳ පරසතුවක් පරිදි                            මහා", "metaphorical_term": "", "source_domain": "", "target_domain": "", "interpretation": ""}
{"index": {"_index": "metaphoem"}}
{"poem_name": "කවියා", "poet": "ආර්.සරණසේකර", "year": "", "poem_line": "විකසිත මලෙකි කිවිඳුයැ කියනා                    මිනිහා", "metaphorical_term": "විකසිත මලෙකි කිවිඳිය කියනා මිනිසා", "source_domain": "කවියා", "target_domain": "විකසිත මල", "interpretation": "කවියා පිපුණු මලක් සේ සුන්දර බව"}
{"index": {"_index": "metaphoem"}}
{"poem_name": "සිතිවිලි සයුර", "poet": "වීරසිංහ මල්ලිමාරච්චි", "year": "1993", "poem_line": "එරබදු මල් මෙවුල මිහිලිය බඳින            ඉණේ", "metaphorical_term": "එරබදු මල් මෙවුල්", "source_domain": "එරබදු මල්", "target_domain": "මණි මේඛලාව", "interpretation": "එරබදු මල් වල අලංකාරය පෙන්වීමට පොලව නම් කාන්තාවට මිණි මෙවුලක් පැලඳුවා වගේ"}
{"index": {"_index": "metaphoem"}}
{"poem_name": "සිතිවිලි සයුර", "poet": "වීරසිංහ මල්ලිමාරච්චි", "year": "1993", "poem_line": "බක් මස හමන සුළඟින් කම්මැලිව        වැනේ", "metaphorical_term": "", "source_domain": "", "target_domain": "", "interpretation": ""}
{"index": {"_index": "metaphoem"}}
{"poem_name": "සිතිවිලි සයුර", "poet": "වීරසිංහ මල්ලිමාරච්චි", "year": "1993", "poem_line": "මිය ගොස් ළඟදි සිට අවුරුදු දිගැස      සෙනේ", "metaphorical_term": "", "source_domain": "", "target_domain": "", "interpretation": ""}
{"index": {"_index": "metaphoem"}}
{"poem_name": "සිතිවිලි සයුර", "poet": "වීරසිංහ මල්ලිමාරච්චි", "year": "1993", "poem_line": "‍නොදනිමි අපේ ගැමි ආරට කිමද          වුණේ", "metaphorical_term": "", "source_domain": "", "target_domain": "", "interpretation": ""}
{"index": {"_index": "metaphoem"}}
{"poem_name": "සිතිවිලි සයුර", "poet": "වීරසිංහ මල්ලිමාරච්චි", "year": "1993", "poem_line": "මියැදුණු මුතුන් මිත්තන් අපට හිමි         කළ", "metaphorical_term": "", "source_domain": "", "target_domain": "", "interpretation": ""}
{"index": {"_index": "metaphoem"}}
{"poem_name": "සිතිවිලි සයුර", "poet": "වීරසිංහ මල්ලිමාරච්චි", "year": "1993", "poem_line": "නැතිවිය පැරණි සිංහල සිරිත් මිණි         වැල", "metaphorical_term": "පැරණි සිංහල සිරිත් මිණිවැල", "source_domain": "පැරණි සිංහල සිරිත්", "target_domain": "මිණි වැල", "interpretation": "පැරණි සිංහල සිරිත් මැණික් මෙන් වටින ඒවා වෙයි"}
{"index": {"_index": "metaphoem"}}
{"poem_name": "සිතිවිලි සයුර", "poet": "වීරසිංහ මල්ලිමාරච්චි", "year": "1993", "poem_line": "ඉහිරුණු කිරට වැළැපී කිමද ඇති           පල", "metaphorical_term": "", "source_domain": "", "target_domain": "", "interpretation": ""}
{"index": {"_index": "metaphoem"}}
{"poem_name": "සිතිවිලි සයුර", "poet": "වීරසිංහ මල්ලිමාරච්චි", "year": "1993", "poem_line": "පුදුමයි අලුත් අවුරුද්දකට ගිය               කල", "metaphorical_term": "", "source_domain": "", "target_domain": "", "interpretation": ""}
{"index": {"_index": "metaphoem"}}
{"poem_name": "කවි හබ", "poet": "ඇලපාත මුදලි", "year": "1800", "poem_line": "මනහර නුඹෙ පවව්‍ර සිරි පිරි වත තඹර", "metaphorical_term": "වත තඹර", "source_domain": "වත", "target_domain": "තඹර", "interpretation": "මුහුණ නෙළුම් මලක් මෙන් සුන්දරයි"}
{"index": {"_index": "metaphoem"}}
{"poem_name": "කවි හබ", "poet": "ඇලපාත මුදලි", "year": "1800", "poem_line": "බොහොවර කින් නුදුටුයෙන් මා නෙත් බමර", "metaphorical_term": "", "source_domain": "", "target_domain": "", "interpretation": ""}
{"index": {"_index": "metaphoem"}}
{"poem_name": "කවි හබ", "poet": "ඇලපාත මුදලි", "year": "1800", "poem_line": "කරදර කර හඬන දිට නලවන අයුර", "metaphorical_term": "", "source_domain": "", "target_domain": "", "interpretation": ""}
{"index": {"_index": "metaphoem"}}
{"poem_name": "කවි හබ", "poet": "ඇලපාත මුදලි", "year": "1800", "poem_line": "නො විසිර මට වහා දන්වන්නේ විතර", "metaphorical_term": "", "source_domain": "", "target_domain": "", "interpretation": ""}
{"index": {"_index": "metaphoem"}}
{"poem_name": "දැඩිතර සෝකමාලය - කොළොම්පුර වැනුම", "poet": "ගජමන් නෝනා", "year": "1800", "poem_line": "නෙත් නිලුපුල් යුතී", "metaphorical_term": "නෙත් නිලුපුල්", "source_domain": "නෙත්", "target_domain": "නිලුපුල්", "interpretation": "නිල් මානෙල් මල් වගේ නෙත් ඉතාමත් සුන්දරයි"}
{"index": {"_index": "metaphoem"}}
{"poem_name": "දැඩිතර සෝකමාලය - කොළොම්පුර වැනුම", "poet": "ගජමන් නෝනා", "year": "1800", "poem_line": "රත් තොල් නා පබළු පෙතී", "metaphorical_term": "රත් තොල් නා පබළු පෙතී", "source_domain": "තොල්", "target_domain": "නා පබළු පෙතී", "interpretation": "නා දලු මෙන් තොල් වල සුන්දර බව කියවෙයි"}
{"index": {"_index": "metaphoem"}}
{"poem_name": "දැඩිතර සෝකමාලය - කොළොම්පුර වැනුම", "poet": "ගජමන් නෝනා", "year": "1800", "poem_line": "දත් ,උතු සෙ දිලෙතී", "metaphorical_term": "", "source_domain": "", "target_domain": "", "interpretation": ""}
{"index": {"_index": "metaphoem"}}
{"poem_name": "දැඩිතර සෝකමාලය - කොළොම්පුර වැනුම", "poet": "ගජමන් නෝනා", "year": "1800", "poem_line": "කොමල සුදු සිනිඳු සියගත ඇතී", "metaphorical_term": "", "source_domain": "", "target_domain": "", "interpretation": ""}
{"index": {"_index": "metaphoem"}}
{"poem_name": "දැඩිතර සෝකමාලය - වන වැනුම", "poet": "ගජමන් නෝනා", "year": "1800", "poem_line": "කලහස මිලින හස", "metaphorical_term": "", "source_domain": "", "target_domain": "", "interpretation": ""}
{"index": {"_index": "metaphoem"}}
{"poem_name": "දැඩිතර සෝකමාලය - වන වැනුම", "poet": "ගජමන් නෝනා", "year": "1800", "poem_line": "සුරත් පා තුඬු රන හස", "metaphorical_term": "පා තුඬු රණ හස", "source_domain": "පා තුඩු", "target_domain": "රණ හස", "interpretation": "පාද දෙක රන් හංසයින් මෙන් කඩිසර බව"}
{"index": {"_index": "metaphoem"}}
{"poem_name": "දැඩිතර සෝකමාලය - වන වැනුම", "poet": "ගජමන් නෝනා", "year": "1800", "poem_line": "පියුමැතියේ පිවිස", "metaphorical_term": "", "source_domain": "", "target_domain": "", "interpretation": ""}
{"index": {"_index": "metaphoem"}}
{"poem_name": "දැඩිතර සෝකමාලය - වන වැනුම", "poet": "ගජමන් නෝනා", "year": "1800", "poem_line": "පොකුරු මී බොන එ දැක වන දෙස", "metaphorical_term": "", "source_domain": "", "target_domain": "", "interpretation": ""}
{"index": {"_index": "metaphoem"}}
{"poem_name": "දැඩිතර සෝකමාලය - වන වැනුම", "poet": "ගජමන් නෝනා", "year": "1800", "poem_line": "එවන ලිය ලිය ලිය", "metaphorical_term": "", "source_domain": "", "target_domain": "", "interpretation": ""}
{"index": {"_index": "metaphoem"}}
{"poem_name": "දැඩිතර සෝකමාලය - වන වැනුම", "poet": "ගජමන් නෝනා", "year": "1800", "poem_line": "වැලඳ තුරු හිමි නිස ලිය", "metaphorical_term": "තුරු හිමි", "source_domain": "තුරු", "target_domain": "හිමි", "interpretation": "වැල් ගස් වටා එතී තිබෙන්නේ කාන්තාවක් තව හිමියන් වැලඳගන්නා සේය"}
{"index": {"_index": "metaphoem"}}
{"poem_name": "දැඩිතර සෝකමාලය - වන වැනුම", "poet": "ගජමන් නෝනා", "year": "1800", "poem_line": "පවන වැඳ සසලිය", "metaphorical_term": "", "source_domain": "", "target_domain": "", "interpretation": ""}
{"index": {"_index": "metaphoem"}}
{"poem_name": "දැඩිතර සෝකමාලය - වන වැනුම", "poet": "ගජමන් නෝනා", "year": "1800", "poem_line": "එවන ගැබ රඟ මඬුලු සිරිලිය", "metaphorical_term": "එවන ගැබ රඟ මඩුලු", "source_domain": "වනාන්තරය", "target_domain": "රඟ මඩල", "interpretation": "රඟ මඬලක් සෙ අලංකාරවූ වනාන්තරය"}
{"index": {"_index": "metaphoem"}}
{"poem_name": "දැඩිතර සෝකමාලය - අගමැති වැනුම", "poet": "ගජමන් නෝනා", "year": "1800", "poem_line": "දිළිඳුන් හට නිතර", "metaphorical_term": "", "source_domain": "", "target_domain": "", "interpretation": ""}
{"index": {"_index": "metaphoem"}}
{"poem_name": "දැඩිතර සෝකමාලය - අගමැති වැනුම", "poet": "ගජමන් නෝනා", "year": "1800", "poem_line": "තිළිණෙන් යුගත සුරතුර", "metaphorical_term": "යුගත සුරතුර", "source_domain": "දෑත", "target_domain": "සුරතුර", "interpretation": "සිතූ පැතූ සම්පත් ලබාදෙන සුරතුර වැනිය දෙඅත"}
{"index": {"_index": "metaphoem"}}
{"poem_name": "දැඩිතර සෝකමාලය - අගමැති වැනුම", "poet": "ගජමන් නෝනා", "year": "1800", "poem_line": "සුගුණෙන සිසිර කර", "metaphorical_term": "", "source_domain": "", "target_domain": "", "interpretation": ""}
{"index": {"_index": "metaphoem"}}
{"poem_name": "දැඩිතර සෝකමාලය - අගමැති වැනුම", "poet": "ගජමන් නෝනා", "year": "1800", "poem_line": "උතුම් අගමැති තුමා පින්සර", "metaphorical_term": "", "source_domain": "", "target_domain": "", "interpretation": ""}
{"index": {"_index": "metaphoem"}}
{"poem_name": "දැඩිතර සෝකමාලය - අගමැති වැනුම", "poet": "ගජමන් නෝනා", "year": "1800", "poem_line": "නෙක අනඬු දුසිරී", "metaphorical_term": "", "source_domain": "", "target_domain": "", "interpretation": ""}
{"index": {"_index": "metaphoem"}}
{"poem_name": "දැඩිතර සෝකමාලය - අගමැති වැනුම", "poet": "ගජමන් නෝනා", "year": "1800", "poem_line": "දුරු කරවමින් අපිරී", "metaphorical_term": "", "source_domain": "", "target_domain": "", "interpretation": ""}
{"index": {"_index": "metaphoem"}}
{"poem_name": "දැඩිතර සෝකමාලය - අගමැති වැනුම", "poet": "ගජමන් නෝනා", "year": "1800", "poem_line": "අගමැති සඳ සිරී", "metaphorical_term": "අගමැති සඳ", "source_domain": "අගමැති", "target_domain": "සඳ", "interpretation": "අගමැති තුමාගේ කරුණාවන්ත බව සහ ඉවසිලිවන්ත බද"}
{"index": {"_index": "metaphoem"}}
{"poem_name": "දැඩිතර සෝකමාලය - අගමැති වැනුම", "poet": "ගජමන් නෝනා", "year": "1800", "poem_line": "වෙසෙත සත වෙත කුළුණු පැතිරී", "metaphorical_term": "", "source_domain": "", "target_domain": "", "interpretation": ""}
{"index": {"_index": "metaphoem"}}
{"poem_name": "චණ්ඩාලී", "poet": "අමරාංගනී විමලවීර", "year": "2002", "poem_line": "කුමරුනි හරිම සොඳුරුයි ගැමි පරි සරය", "metaphorical_term": "", "source_domain": "", "target_domain": "", "interpretation": ""}
{"index": {"_index": "metaphoem"}}
{"poem_name": "චණ්ඩාලී", "poet": "අමරාංගනී විමලවීර", "year": "2002", "poem_line": "රූබර ලියන් දෙව්ලියො මෙනි සුර පුරය ", "metaphorical_term": "", "source_domain": "", "target_domain": "", "interpretation": ""}
{"index": {"_index": "metaphoem"}}
{"poem_name": "චණ්ඩාලී", "poet": "අමරාංගනී විමලවීර", "year": "2002", "poem_line": "විඳගමු සොඳුරු සුව විහිදමු නෙත් සැරය", "metaphorical_term": "", "source_domain": "", "target_domain": "", "interpretation": ""}
{"index": {"_index": "metaphoem"}}
{"poem_name": "චණ්ඩාලී", "poet": "අමරාංගනී විමලවීර", "year": "2002", "poem_line": "පිය රජතුමා හමු වී අරගමු වරය", "metaphorical_term": "", "source_domain": "", "target_domain": "", "interpretation": ""}
{"index": {"_index": "metaphoem"}}
{"poem_name": "චණ්ඩාලී", "poet": "අමරාංගනී විමලවීර", "year": "2002", "poem_line": "වෙලෙමින් තුඩින් තුඩ පා කිචි බිචි නාදේ", "metaphorical_term": "", "source_domain": "", "target_domain": "", "interpretation": ""}
{"index": {"_index": "metaphoem"}}
{"poem_name": "චණ්ඩාලී", "poet": "අමරාංගනී විමලවීර", "year": "2002", "poem_line": "දිහඟුන් අතු පතර හිඳ පැටලෙයි වාදේ", "metaphorical_term": "", "source_domain": "", "target_domain": "", "interpretation": ""}
{"index": {"_index": "metaphoem"}}
{"poem_name": "චණ්ඩාලී", "poet": "අමරාංගනී විමලවීර", "year": "2002", "poem_line": "විහිදා කිරණ හිරු හිනැහෙයි ගඟ නෝදේ", "metaphorical_term": "", "source_domain": "", "target_domain": "", "interpretation": ""}
{"index": {"_index": "metaphoem"}}
{"poem_name": "චණ්ඩාලී", "poet": "අමරාංගනී විමලවීර", "year": "2002", "poem_line": "මඟුලකි, එකම මඟුලකි ඒ අරු ණෝදේ ", "metaphorical_term": "මඟුලකි අරුණෝදේ", "source_domain": "උදය", "target_domain": "මඟුල", "interpretation": "උදෑසන සිරිය සහ කලබලය මඟුල් අවස්ථාවක් සේ දකියි."}
{"index": {"_index": "metaphoem"}}
{"poem_name": "චණ්ඩාලී", "poet": "අමරාංගනී විමලවීර", "year": "2002", "poem_line": "නෙති සිත් නිවයි තැන තැන ඇත තුරු සපේලී", "metaphorical_term": "", "source_domain": "", "target_domain": "", "interpretation": ""}
{"index": {"_index": "metaphoem"}}
{"poem_name": "චණ්ඩාලී", "poet": "අමරාංගනී විමලවීර", "year": "2002", "poem_line": "කුලහීනය දනන් එහි විසු හෙල් ලෝලී", "metaphorical_term": "", "source_domain": "", "target_domain": "", "interpretation": ""}
{"index": {"_index": "metaphoem"}}
{"poem_name": "චණ්ඩාලී", "poet": "අමරාංගනී විමලවීර", "year": "2002", "poem_line": "රුසිරෙන් අනූන ය රූබර මනමාලී", "metaphorical_term": "", "source_domain": "", "target_domain": "", "interpretation": ""}
{"index": {"_index": "metaphoem"}}
{"poem_name": "චණ්ඩාලී", "poet": "අමරාංගනී විමලවීර", "year": "2002", "poem_line": "මාලා දෙව්දුවකි, මොකට ද බොරු හෑලී ", "metaphorical_term": "මාලා දෙව්දුවකි", "source_domain": "අශෝකමාලා", "target_domain": "දෙව්දුව", "interpretation": "අශෝකමාලාගේ සුන්දරත්වය දෙව්දුවක් මෙන් පෙනෙන බව"}
{"index": {"_index": "metaphoem"}}
{"poem_name": "චණ්ඩාලී", "poet": "අමරාංගනී විමලවීර", "year": "2002", "poem_line": "ඇති හොඳටෝම දඟ වැඩ කරුමය ද මොන", "metaphorical_term": "", "source_domain": "", "target_domain": "", "interpretation": ""}
{"index": {"_index": "metaphoem"}}
{"poem_name": "චණ්ඩාලී", "poet": "අමරාංගනී විමලවීර", "year": "2002", "poem_line": "ගැසුවා අතුල් පහරක් ඉදිරියට පැන", "metaphorical_term": "", "source_domain": "", "target_domain": "", "interpretation": ""}
{"index": {"_index": "metaphoem"}}
{"poem_name": "චණ්ඩාලී", "poet": "අමරාංගනී විමලවීර", "year": "2002", "poem_line": "කොක්හඬ දිදී රඟ දී තරඟයට මෙන", "metaphorical_term": "", "source_domain": "", "target_domain": "", "interpretation": ""}
{"index": {"_index": "metaphoem"}}
{"poem_name": "චණ්ඩාලී", "poet": "අමරාංගනී විමලවීර", "year": "2002", "poem_line": "නව යෞවනය මිහිරකි, රස මිහිර දෙන", "metaphorical_term": "නව යෞවනය මිහිරකි", "source_domain": "යොවුන් බව", "target_domain": "මිහිර", "interpretation": "යෞවනයේ රසින් මත් වී ඇති බව"}
{"index": {"_index": "metaphoem"}}
{"poem_name": "චණ්ඩාලී", "poet": "අමරාංගනී විමලවීර", "year": "2002", "poem_line": "දුටු දසුනින් ම විය නුපුරුදු ගතිය හදේ", "metaphorical_term": "", "source_domain": "", "target_domain": "", "interpretation": ""}
{"index": {"_index": "metaphoem"}}
{"poem_name": "චණ්ඩාලී", "poet": "අමරාංගනී විමලවීර", "year": "2002", "poem_line": "වසඟ ව යනු දැනේ මගෙ හද ඔබට තදේ", "metaphorical_term": "", "source_domain": "", "target_domain": "", "interpretation": ""}
{"index": {"_index": "metaphoem"}}
{"poem_name": "චණ්ඩාලී", "poet": "අමරාංගනී විමලවීර", "year": "2002", "poem_line": "ඔබෙ වත සුපිපි කුසුමකි මෙහි පිපුණ උදේ", "metaphorical_term": "වත සුපිපි කුසුමක", "source_domain": "වත", "target_domain": "කුසුම", "interpretation": "මුහුනේ සුන්දරත්වය උදේ පිපුනු මලක් මෙනි"}
{"index": {"_index": "metaphoem"}}
{"poem_name": "චණ්ඩාලී", "poet": "අමරාංගනී විමලවීර", "year": "2002", "poem_line": "මා හට කියනු සොයුරිය, තී කව්ද ළඳේ", "metaphorical_term": "", "source_domain": "", "target_domain": "", "interpretation": ""}
{"index": {"_index": "metaphoem"}}
{"poem_name": "චණ්ඩාලී", "poet": "අමරාංගනී විමලවීර", "year": "2002", "poem_line": "ඔබ හා බැඳුණු සිත නැහැ ඉවතට ලන්නේ", "metaphorical_term": "", "source_domain": "", "target_domain": "", "interpretation": ""}
{"index": {"_index": "metaphoem"}}
{"poem_name": "චණ්ඩාලී", "poet": "අමරාංගනී විමලවීර", "year": "2002", "poem_line": "මාලා මැණික ඇයි මගෙ සිත පා රන්නේ", "metaphorical_term": "මාලා මැණික", "source_domain": "අශෝකමාලා", "target_domain": "මැණික", "interpretation": "අශෝකමාලාව ඉතාමත් වටින බව මෙයින් කියවේ"}
{"index": {"_index": "metaphoem"}}
{"poem_name": "චණ්ඩාලී", "poet": "අමරාංගනී විමලවීර", "year": "2002", "poem_line": "අන් කුමරියක කෙලෙස ද සරණෙට ගන්නේ", "metaphorical_term": "", "source_domain": "", "target_domain": "", "interpretation": ""}
{"index": {"_index": "metaphoem"}}
{"poem_name": "චණ්ඩාලී", "poet": "අමරාංගනී විමලවීර", "year": "2002", "poem_line": "ඔබෙ සිත රැගෙන මිස මම යළි නැහැ යන්නේ", "metaphorical_term": "", "source_domain": "", "target_domain": "", "interpretation": ""}
{"index": {"_index": "metaphoem"}}
{"poem_name": "චණ්ඩාලී", "poet": "අමරාංගනී විමලවීර", "year": "2002", "poem_line": "නසමිද කෙලෙස මේ දිගැසිය රුවට රුවයි", "metaphorical_term": "", "source_domain": "", "target_domain": "", "interpretation": ""}
{"index": {"_index": "metaphoem"}}
{"poem_name": "චණ්ඩාලී", "poet": "අමරාංගනී විමලවීර", "year": "2002", "poem_line": "මිණි කිංකිණි නදින් හද ගිම් පවස නිවයි", "metaphorical_term": "", "source_domain": "", "target_domain": "", "interpretation": ""}
{"index": {"_index": "metaphoem"}}
{"poem_name": "චණ්ඩාලී", "poet": "අමරාංගනී විමලවීර", "year": "2002", "poem_line": "රජ කුමරියක පරදා විරු ගතිය මවයි", "metaphorical_term": "", "source_domain": "", "target_domain": "", "interpretation": ""}
{"index": {"_index": "metaphoem"}}
{"poem_name": "චණ්ඩාලී", "poet": "අමරාංගනී විමලවීර", "year": "2002", "poem_line": "දිදුලන තරුව ඇය, සාලිය කුමරු ලොවයි", "metaphorical_term": "දිදුලන තරුව ඇය", "source_domain": "ඇය", "target_domain": "තරුව", "interpretation": "අශෝකමාලාවගේ සුන්දර බව දිදුලන තරුවක් සේ දැක ඇත"}
{"index": {"_index": "metaphoem"}}
{"poem_name": "චණ්ඩාලී", "poet": "අමරාංගනී විමලවීර", "year": "2002", "poem_line": "කළ මෙහෙවර දැයට සෙනෙහස ඇති ව ළයේ", "metaphorical_term": "", "source_domain": "", "target_domain": "", "interpretation": ""}
{"index": {"_index": "metaphoem"}}
{"poem_name": "චණ්ඩාලී", "poet": "අමරාංගනී විමලවීර", "year": "2002", "poem_line": "පිය රජු මගේ, මා හැඟි සිතුමිණකි දැයේ", "metaphorical_term": "පිය රජු මගේ මා හැඟි සිතුමිණකි", "source_domain": "පියරජු", "target_domain": "සිතුමිණ", "interpretation": "පියාණන් යනු මෙහි ගැමුණු රජුයි. ඔහුව සිතූ පැතූ සම්පත් දෙන මැණිකක් මෙන් වටී"}
{"index": {"_index": "metaphoem"}}
{"poem_name": "චණ්ඩාලී", "poet": "අමරාංගනී විමලවීර", "year": "2002", "poem_line": "මාලාවනි මගේ ලොව මිණි කිරුළ පියේ", "metaphorical_term": "", "source_domain": "", "target_domain": "", "interpretation": ""}
{"index": {"_index": "metaphoem"}}
{"poem_name": "චණ්ඩාලී", "poet": "අමරාංගනී විමලවීර", "year": "2002", "poem_line": "ඔබ ගැන තතු හැඳින පිය රජු ඉවත ගියේ", "metaphorical_term": "", "source_domain": "", "target_domain": "", "interpretation": ""}
{"index": {"_index": "metaphoem"}}
{"poem_name": "චණ්ඩාලී", "poet": "අමරාංගනී විමලවීර", "year": "2002", "poem_line": "හද ගිම් නිමවමින් මුදු පවනැලි වීදේ", "metaphorical_term": "", "source_domain": "", "target_domain": "", "interpretation": ""}
{"index": {"_index": "metaphoem"}}
{"poem_name": "චණ්ඩාලී", "poet": "අමරාංගනී විමලවීර", "year": "2002", "poem_line": "මල් ගොමු අතර ඇසුණා, බිඟුනගෙ සාදේ", "metaphorical_term": "", "source_domain": "", "target_domain": "", "interpretation": ""}
{"index": {"_index": "metaphoem"}}
{"poem_name": "චණ්ඩාලී", "poet": "අමරාංගනී විමලවීර", "year": "2002", "poem_line": "මාලා නැඟූ හසරැලි කිංකිණි නාදේ", "metaphorical_term": "හසරැලි කිංකිණි", "source_domain": "හසරැලි", "target_domain": "කිංකිණි", "interpretation": "සිනහව ඉතාම සුන්දර බැවින් මිණිගෙඩි වල ශබ්දය ලෙස පවසා තිබේ"}
{"index": {"_index": "metaphoem"}}
{"poem_name": "චණ්ඩාලී", "poet": "අමරාංගනී විමලවීර", "year": "2002", "poem_line": "මිහිරෙන් සැනසිලා අතු අග මල් පීදේ", "metaphorical_term": "", "source_domain": "", "target_domain": "", "interpretation": ""}
{"index": {"_index": "metaphoem"}}
{"poem_name": "සිතිවිලි සයුර", "poet": "වීරසිංහ මල්ලිමාරච්චි", "year": "1993", "poem_line": "සිතිවිලි සතුරු ගෙල ලූ වදමල් වැලය", "metaphorical_term": "", "source_domain": "", "target_domain": "", "interpretation": ""}
{"index": {"_index": "metaphoem"}}
{"poem_name": "සිතිවිලි සයුර", "poet": "වීරසිංහ මල්ලිමාරච්චි", "year": "1993", "poem_line": "පන්හිඳ සුරත ලැගි මුවහත කඩු තලය", "metaphorical_term": "පන්හිඳ මුවහත් කඩුතලය", "source_domain": "පන්හිඳ", "target_domain": "කඩුව", "interpretation": "පෑනෙන් කල හැකි දස්කම් වල තරම කඩුවේ මුවහත් බව ලෙස දක්වයි"}
{"index": {"_index": "metaphoem"}}
{"poem_name": "සිතිවිලි සයුර", "poet": "වීරසිංහ මල්ලිමාරච්චි", "year": "1993", "poem_line": "ජන සම්මතය ලද රට කරවන බලය", "metaphorical_term": "", "source_domain": "", "target_domain": "", "interpretation": ""}
{"index": {"_index": "metaphoem"}}
{"poem_name": "සිතිවිලි සයුර", "poet": "වීරසිංහ මල්ලිමාරච්චි", "year": "1993", "poem_line": "උපතින් උරුම වූ පරපුර කවි කුලය", "metaphorical_term": "", "source_domain": "", "target_domain": "", "interpretation": ""}
{"index": {"_index": "metaphoem"}}
{"poem_name": "සිතිවිලි සයුර", "poet": "වීරසිංහ මල්ලිමාරච්චි", "year": "1993", "poem_line": "දවසක ඉසුරුමත් කල හැකි ජන දිවිය", "metaphorical_term": "", "source_domain": "", "target_domain": "", "interpretation": ""}
{"index": {"_index": "metaphoem"}}
{"poem_name": "සිතිවිලි සයුර", "poet": "වීරසිංහ මල්ලිමාරච්චි", "year": "1993", "poem_line": "දුක හඳුනන සිතය කවියකු සතු සවිය", "metaphorical_term": "", "source_domain": "", "target_domain": "", "interpretation": ""}
{"index": {"_index": "metaphoem"}}
{"poem_name": "සිතිවිලි සයුර", "poet": "වීරසිංහ මල්ලිමාරච්චි", "year": "1993", "poem_line": "වැදගත් කුල දුවකි ඔහුගේ සර සවිය", "metaphorical_term": "කුලදුවකි ඔහුගේ සරසවිය", "source_domain": "සරසවිය", "target_domain": "කුලදුව", "interpretation": "සරසවිය යනු මෙහි කවි හැකියාවයි. එහි ඇති වැදගත් බව මෙයින් කියවෙයි"}
{"index": {"_index": "metaphoem"}}
{"poem_name": "සිතිවිලි සයුර", "poet": "වීරසිංහ මල්ලිමාරච්චි", "year": "1993", "poem_line": "ඇය රත් ලවන පිපි මල් මදහස කවිය", "metaphorical_term": "මල් මදහස කවිය", "source_domain": "කවිය", "target_domain": "මල් මදහස", "interpretation": "කවිය මද සිනහවක් වගේ සුන්දරයි"}
{"index": {"_index": "metaphoem"}}
{"poem_name": "සිතිවිලි සයුර", "poet": "වීරසිංහ මල්ලිමාරච්චි", "year": "1993", "poem_line": "බිඳ බැඳි වහල් බැමි බැළ මෙහෙ කළ දිවිය", "metaphorical_term": "", "source_domain": "", "target_domain": "", "interpretation": ""}
{"index": {"_index": "metaphoem"}}
{"poem_name": "සිතිවිලි සයුර", "poet": "වීරසිංහ මල්ලිමාරච්චි", "year": "1993", "poem_line": "නිද හස දකින දැයකට වූ විදුරවිය", "metaphorical_term": "", "source_domain": "", "target_domain": "", "interpretation": ""}
{"index": {"_index": "metaphoem"}}
{"poem_name": "සිතිවිලි සයුර", "poet": "වීරසිංහ මල්ලිමාරච්චි", "year": "1993", "poem_line": "වඳ වී ගිය දිනක ජන සම්මත සවිය", "metaphorical_term": "", "source_domain": "", "target_domain": "", "interpretation": ""}
{"index": {"_index": "metaphoem"}}
{"poem_name": "සිතිවිලි සයුර", "poet": "වීරසිංහ මල්ලිමාරච්චි", "year": "1993", "poem_line": "අඳ ගොලු බිහිරි වැන්දඹුවකි සරසවිය", "metaphorical_term": "වැන්දඹුවකි සරසවිය", "source_domain": "සරසවිය", "target_domain": "වැන්දඹුව", "interpretation": "සමහර වේලා වලදි කවිය හෙවත් සරසවියටත් කරකියාගත හැක්කක් නොමැත යන අර්ථය"}
{"index": {"_index": "metaphoem"}}
{"poem_name": "සිතිවිලි සයුර", "poet": "වීරසිංහ මල්ලිමාරච්චි", "year": "1993", "poem_line": "දියවන්නා ඔයේ පිරියත රන් දෙරණේ", "metaphorical_term": "", "source_domain": "", "target_domain": "", "interpretation": ""}
{"index": {"_index": "metaphoem"}}
{"poem_name": "සිතිවිලි සයුර", "poet": "වීරසිංහ මල්ලිමාරච්චි", "year": "1993", "poem_line": "මහ රජ දහන දෙව්ලොව රුව දුටු පොරණේ", "metaphorical_term": "මහ රජ දහන දෙව්ලොව", "source_domain": "රජ දහන", "target_domain": "දෙව්ලොව", "interpretation": "රාජධානියේ ශ්‍රියාව ඉතා ඉහළ බැවින් දෙව්ලොව ම යැයි සිතෙයි"}
{"index": {"_index": "metaphoem"}}
{"poem_name": "සිතිවිලි සයුර", "poet": "වීරසිංහ මල්ලිමාරච්චි", "year": "1993", "poem_line": "පස් මහ සඳෙස් හෙල පැදි මිණි බැඳි තොරණේ", "metaphorical_term": "", "source_domain": "", "target_domain": "", "interpretation": ""}
{"index": {"_index": "metaphoem"}}
{"poem_name": "සිතිවිලි සයුර", "poet": "වීරසිංහ මල්ලිමාරච්චි", "year": "1993", "poem_line": "කිවියෝ ලදහ මහ වාසල රැක වරණේ", "metaphorical_term": "", "source_domain": "", "target_domain": "", "interpretation": ""}
{"index": {"_index": "metaphoem"}}
{"poem_name": "සිතිවිලි සයුර", "poet": "වීරසිංහ මල්ලිමාරච්චි", "year": "1993", "poem_line": "රණ කෙළි පිණිස වැද බිය සැක නුමුසු සිත", "metaphorical_term": "", "source_domain": "", "target_domain": "", "interpretation": ""}
{"index": {"_index": "metaphoem"}}
{"poem_name": "සිතිවිලි සයුර", "poet": "වීරසිංහ මල්ලිමාරච්චි", "year": "1993", "poem_line": "ජය ගත් කලා විජිතය බිඳ කුකවි මත", "metaphorical_term": "", "source_domain": "", "target_domain": "", "interpretation": ""}
{"index": {"_index": "metaphoem"}}
{"poem_name": "සිතිවිලි සයුර", "poet": "වීරසිංහ මල්ලිමාරච්චි", "year": "1993", "poem_line": "වරුවන් අදත් මගෙ හෙළ දෑ මවට ඇත", "metaphorical_term": "", "source_domain": "", "target_domain": "", "interpretation": ""}
{"index": {"_index": "metaphoem"}}
{"poem_name": "සිතිවිලි සයුර", "poet": "වීරසිංහ මල්ලිමාරච්චි", "year": "1993", "poem_line": "පන්හිඳ වියත් සුරතෙහි විය රණසි පත", "metaphorical_term": "පන්හිඳ වියත් සුරතේ රන අසිපත", "source_domain": "පන්හිඳ", "target_domain": "රන අසිපත", "interpretation": "පන්හිඳෙන් ලියවෙන දේ රණ අසිපතක් මෙන් ප්‍රභලයි"}
{"index": {"_index": "metaphoem"}}
{"poem_name": "සිතිවිලි සයුර", "poet": "වීරසිංහ මල්ලිමාරච්චි", "year": "1993", "poem_line": "පොදු ජන බමර රොද පසුවූ අඩ නින්දේ ", "metaphorical_term": "පොදු ජන බඹර රොද", "source_domain": "පොදු ජනයා", "target_domain": "බඹරු", "interpretation": "එක ලඟින් ඇසිරී ඇති බව මෙයින් දක්වා ඇත"}
{"index": {"_index": "metaphoem"}}
{"poem_name": "සිතිවිලි සයුර", "poet": "වීරසිංහ මල්ලිමාරච්චි", "year": "1993", "poem_line": "සුවඳින් අවදි කල සිවුපැදි මක රන්දේ", "metaphorical_term": "", "source_domain": "", "target_domain": "", "interpretation": ""}
{"index": {"_index": "metaphoem"}}
{"poem_name": "සිතිවිලි සයුර", "poet": "වීරසිංහ මල්ලිමාරච්චි", "year": "1993", "poem_line": "දැය සරසියේ පිපි කිවි පද අර වින්දේ ", "metaphorical_term": "කිවිපද අරවින්දේ", "source_domain": "කවිපද", "target_domain": "අරවින්ද", "interpretation": "කවියේ සුන්දරත්වය නෙළුමේ සුන්දරත්වයට සමාන කර ඇත"}
{"index": {"_index": "metaphoem"}}
{"poem_name": "සිතිවිලි සයුර", "poet": "වීරසිංහ මල්ලිමාරච්චි", "year": "1993", "poem_line": "නිය රොන් රජුන් නළලත තිලකය ඇන්දේ", "metaphorical_term": "", "source_domain": "", "target_domain": "", "interpretation": ""}
{"index": {"_index": "metaphoem"}}
{"poem_name": "සිතිවිලි සයුර", "poet": "වීරසිංහ මල්ලිමාරච්චි", "year": "1993", "poem_line": "හෙළ සරසවිය ඍඅකි පතිවත බිඳින ඉඟී", "metaphorical_term": "", "source_domain": "", "target_domain": "", "interpretation": ""}
{"index": {"_index": "metaphoem"}}
{"poem_name": "සිතිවිලි සයුර", "poet": "වීරසිංහ මල්ලිමාරච්චි", "year": "1993", "poem_line": "දුටු විට දැයට සිදුවන මහ විපත හැඟී", "metaphorical_term": "", "source_domain": "", "target_domain": "", "interpretation": ""}
{"index": {"_index": "metaphoem"}}
{"poem_name": "සිතිවිලි සයුර", "poet": "වීරසිංහ මල්ලිමාරච්චි", "year": "1993", "poem_line": "සිංහල පැදිය අසිපත වී සුරත ලැගී ", "metaphorical_term": "සිංහල පැදිය අසිපත", "source_domain": "සිංහල කවි", "target_domain": "අසිපත්", "interpretation": "කවියෙහි ප්‍රභලත්වය අසිපතක් ලෙස මින් කියවේ"}
{"index": {"_index": "metaphoem"}}
{"poem_name": "සිතිවිලි සයුර", "poet": "වීරසිංහ මල්ලිමාරච්චි", "year": "1993", "poem_line": "කවියා සතුරු අඹු නෙතු යුග කඳුළු නැගී", "metaphorical_term": "", "source_domain": "", "target_domain": "", "interpretation": ""}
{"index": {"_index": "metaphoem"}}
{"poem_name": "සිතිවිලි සයුර", "poet": "වීරසිංහ මල්ලිමාරච්චි", "year": "1993", "poem_line": "කොළපත රැගෙන ගොස් රජ සිටු මැදුරු වෙත", "metaphorical_term": "", "source_domain": "", "target_domain": "", "interpretation": ""}
{"index": {"_index": "metaphoem"}}
{"poem_name": "සිතිවිලි සයුර", "poet": "වීරසිංහ මල්ලිමාරච්චි", "year": "1993", "poem_line": "දුක කිය කියා ඔහු යසිසුරු අයැද නැත", "metaphorical_term": "", "source_domain": "", "target_domain": "", "interpretation": ""}
{"index": {"_index": "metaphoem"}}
{"poem_name": "සිතිවිලි සයුර", "poet": "වීරසිංහ මල්ලිමාරච්චි", "year": "1993", "poem_line": "කවියා මළත් දෑ කැටපත් තලය මත", "metaphorical_term": "දෑ කැටපත් තලය", "source_domain": "ජාතිය", "target_domain": "කැටපත් තලය", "interpretation": "ජාතිය කැටපත් තලයක් මෙන් පැහැදිලි බව මින් අදහස් වේ"}
{"index": {"_index": "metaphoem"}}
{"poem_name": "සිතිවිලි සයුර", "poet": "වීරසිංහ මල්ලිමාරච්චි", "year": "1993", "poem_line": "ඔහුගේ කුළුණු බර හදවත රැඳෙනු ඇත", "metaphorical_term": "", "source_domain": "", "target_domain": "", "interpretation": ""}
{"index": {"_index": "metaphoem"}}
{"poem_name": "සිතිවිලි සයුර", "poet": "වීරසිංහ මල්ලිමාරච්චි", "year": "1993", "poem_line": "මාතර කිවිඳියට බිහි කළ මිහිරි පැදී", "metaphorical_term": "", "source_domain": "", "target_domain": "", "interpretation": ""}
{"index": {"_index": "metaphoem"}}
{"poem_name": "සිතිවිලි සයුර", "poet": "වීරසිංහ මල්ලිමාරච්චි", "year": "1993", "poem_line": "බත්පත අඳින වත නැතිවුණ සමය කදී", "metaphorical_term": "", "source_domain": "", "target_domain": "", "interpretation": ""}
{"index": {"_index": "metaphoem"}}
{"poem_name": "සිතිවිලි සයුර", "poet": "වීරසිංහ මල්ලිමාරච්චි", "year": "1993", "poem_line": "කොටුවේ රජුට බිරිතනි සිහසුනට ලැදී", "metaphorical_term": "", "source_domain": "", "target_domain": "", "interpretation": ""}
{"index": {"_index": "metaphoem"}}
{"poem_name": "සිතිවිලි සයුර", "poet": "වීරසිංහ මල්ලිමාරච්චි", "year": "1993", "poem_line": "උඹ ගෙල කඳුළු මුතු හර බැඳ යවන ලදී", "metaphorical_term": "කඳුළු මුතුහර", "source_domain": "කඳුළු", "target_domain": "මුතුහර", "interpretation": "කවිය ඉතා සුන්දරව ගලපා ඇතිවිට මුතු පොටක් සේ සුන්දර බව"}
{"index": {"_index": "metaphoem"}}
{"poem_name": "සිතිවිලි සයුර", "poet": "වීරසිංහ මල්ලිමාරච්චි", "year": "1993", "poem_line": "දැය රජ ගෙදර අග මෙහෙසිය සරසවිය", "metaphorical_term": "අග මෙහෙසිය සරසවිය", "source_domain": "සරසවිය", "target_domain": "අග මෙහෙසිය", "interpretation": "අග මෙහෙසිය යනු ප්‍රධානියෙකි. කවිකම හෙවත් සරසවියට ප්‍රධාන ස්ථානයක් ලැබෙන බව මින් කියවේ"}
{"index": {"_index": "metaphoem"}}
{"poem_name": "සිතිවිලි සයුර", "poet": "වීරසිංහ මල්ලිමාරච්චි", "year": "1993", "poem_line": "ජයගත් සතුරු විජිතය බස විදු රවිය", "metaphorical_term": "", "source_domain": "", "target_domain": "", "interpretation": ""}
{"index": {"_index": "metaphoem"}}
{"poem_name": "සිතිවිලි සයුර", "poet": "වීරසිංහ මල්ලිමාරච්චි", "year": "1993", "poem_line": "සිහසුන වඩා හිඳුවා පොදු ජන දිවිය", "metaphorical_term": "", "source_domain": "", "target_domain": "", "interpretation": ""}
{"index": {"_index": "metaphoem"}}
{"poem_name": "සිතිවිලි සයුර", "poet": "වීරසිංහ මල්ලිමාරච්චි", "year": "1993", "poem_line": "සිංහල හිසට මුතු කුඩයක් විය කවිය", "metaphorical_term": "මුතු කුඩයක් විය කවිය", "source_domain": "කවිය", "target_domain": "මුතුකුඩය", "interpretation": "කවිය සිංහලකමට ආරාක්ෂාවක් සහ වටිනාකමක් බව"}
{"index": {"_index": "metaphoem"}}
{"poem_name": "සිතිවිලි සයුර", "poet": "වීරසිංහ මල්ලිමාරච්චි", "year": "1993", "poem_line": "අවුරුද්දෙන් අඩක් තද නියඟයට පැහී", "metaphorical_term": "", "source_domain": "", "target_domain": "", "interpretation": ""}
{"index": {"_index": "metaphoem"}}
{"poem_name": "සිතිවිලි සයුර", "poet": "වීරසිංහ මල්ලිමාරච්චි", "year": "1993", "poem_line": "කන්නෙට වැටෙන විට බැඳ ගෙන වහින වැහී", "metaphorical_term": "", "source_domain": "", "target_domain": "", "interpretation": ""}
{"index": {"_index": "metaphoem"}}
{"poem_name": "සිතිවිලි සයුර", "poet": "වීරසිංහ මල්ලිමාරච්චි", "year": "1993", "poem_line": "අබලන් ඉළුක් වහලින් ගෙට වතුර බහී", "metaphorical_term": "", "source_domain": "", "target_domain": "", "interpretation": ""}
{"index": {"_index": "metaphoem"}}
{"poem_name": "සිතිවිලි සයුර", "poet": "වීරසිංහ මල්ලිමාරච්චි", "year": "1993", "poem_line": "මූසල හිඟනකම සක්විති රජෙකි මෙහී ", "metaphorical_term": "හිඟනකම සක්විති රජෙකි", "source_domain": "හිඟනකම", "target_domain": "සක්විති රජ", "interpretation": "අපහසුවෙන් දිවිගෙවන්නන් හට නැතිබැරිකමත් වටිනකමකි"}
{"index": {"_index": "metaphoem"}}
{"poem_name": "සිතිවිලි සයුර", "poet": "වීරසිංහ මල්ලිමාරච්චි", "year": "1993", "poem_line": "මදහස නගන නව යුගයක මුහුණු වර", "metaphorical_term": "", "source_domain": "", "target_domain": "", "interpretation": ""}
{"index": {"_index": "metaphoem"}}
{"poem_name": "සිතිවිලි සයුර", "poet": "වීරසිංහ මල්ලිමාරච්චි", "year": "1993", "poem_line": "බුදු මැදුරක සෙවණ ඇත ගෙට පෙනෙන දුර", "metaphorical_term": "", "source_domain": "", "target_domain": "", "interpretation": ""}
{"index": {"_index": "metaphoem"}}
{"poem_name": "සිතිවිලි සයුර", "poet": "වීරසිංහ මල්ලිමාරච්චි", "year": "1993", "poem_line": "දහදුක් විඳින ලද පොල් අතු පැලක පෙර", "metaphorical_term": "", "source_domain": "", "target_domain": "", "interpretation": ""}
{"index": {"_index": "metaphoem"}}
{"poem_name": "සිතිවිලි සයුර", "poet": "වීරසිංහ මල්ලිමාරච්චි", "year": "1993", "poem_line": "දුටුවෙමි ගෙහිමි නෙත බැඳි තුටු කඳුළු හර ", "metaphorical_term": "තුටු කඳුළු හර", "source_domain": "තුටුකඳුළු", "target_domain": "හර", "interpretation": "සතුටු කඳුළු වලට වටිනාකමක් ලබාදී ඇත"}
{"index": {"_index": "metaphoem"}}
{"poem_name": "සිතිවිලි සයුර", "poet": "වීරසිංහ මල්ලිමාරච්චි", "year": "1993", "poem_line": "පැදි මිණි මෙවුල වැල බැඳි සරසවිය ඉඟේ ", "metaphorical_term": "පැදි මිණි මෙවුල", "source_domain": "කවි", "target_domain": "මිණි මෙවුල", "interpretation": "කවියට විශාල වටිනාකමක් ලබාදී ඇත"}
{"index": {"_index": "metaphoem"}}
{"poem_name": "සිතිවිලි සයුර", "poet": "වීරසිංහ මල්ලිමාරච්චි", "year": "1993", "poem_line": "සත්සර විරිත් ජය ගත් වැහි ලිහිණි දඟේ", "metaphorical_term": "", "source_domain": "", "target_domain": "", "interpretation": ""}
{"index": {"_index": "metaphoem"}}
{"poem_name": "සිතිවිලි සයුර", "poet": "වීරසිංහ මල්ලිමාරච්චි", "year": "1993", "poem_line": "උපතින් උරුම සිංහල ජාතියට මගේ", "metaphorical_term": "", "source_domain": "", "target_domain": "", "interpretation": ""}
{"index": {"_index": "metaphoem"}}
{"poem_name": "සිතිවිලි සයුර", "poet": "වීරසිංහ මල්ලිමාරච්චි", "year": "1993", "poem_line": "ලොකු වස්තුවක් නොතිබිණි රස කවිය වගේ", "metaphorical_term": "", "source_domain": "", "target_domain": "", "interpretation": ""}
{"index": {"_index": "metaphoem"}}
{"poem_name": "සිතිවිලි සයුර", "poet": "වීරසිංහ මල්ලිමාරච්චි", "year": "1993", "poem_line": "රන්දෙණිගල මාදුරු ඔය කොත්මලය", "metaphorical_term": "", "source_domain": "", "target_domain": "", "interpretation": ""}
{"index": {"_index": "metaphoem"}}
{"poem_name": "සිතිවිලි සයුර", "poet": "වීරසිංහ මල්ලිමාරච්චි", "year": "1993", "poem_line": "කන්නෙට බඳි කුඹුරට මහවැලි ජලය", "metaphorical_term": "", "source_domain": "", "target_domain": "", "interpretation": ""}
{"index": {"_index": "metaphoem"}}
{"poem_name": "සිතිවිලි සයුර", "poet": "වීරසිංහ මල්ලිමාරච්චි", "year": "1993", "poem_line": "මුතු සේසත වහල සිහසුන අගු පිලය ", "metaphorical_term": "සිහසුන අගුපිලය", "source_domain": "අගුපිල", "target_domain": "සිහසුන", "interpretation": "ගොවියාගේ නිවහනට ඉතා වැදගත් ස්ථානයක් බව මෙයින් පෙනෙයි"}
{"index": {"_index": "metaphoem"}}
{"poem_name": "සිතිවිලි සයුර", "poet": "වීරසිංහ මල්ලිමාරච්චි", "year": "1993", "poem_line": "අද රජවරුය ගොවිතැන් බත් කළ කුලය", "metaphorical_term": "", "source_domain": "", "target_domain": "", "interpretation": ""}
{"index": {"_index": "metaphoem"}}
{"poem_name": "සිතිවිලි සයුර", "poet": "වීරසිංහ මල්ලිමාරච්චි", "year": "1993", "poem_line": "දහමින් ගැටළු තැන් එක මොහොතින් විසඳු", "metaphorical_term": "", "source_domain": "", "target_domain": "", "interpretation": ""}
{"index": {"_index": "metaphoem"}}
{"poem_name": "සිතිවිලි සයුර", "poet": "වීරසිංහ මල්ලිමාරච්චි", "year": "1993", "poem_line": "දුහුනන් පිණිස පොත පත ලීමෙහි පුරුදු", "metaphorical_term": "", "source_domain": "", "target_domain": "", "interpretation": ""}
{"index": {"_index": "metaphoem"}}
{"poem_name": "සිතිවිලි සයුර", "poet": "වීරසිංහ මල්ලිමාරච්චි", "year": "1993", "poem_line": "අවමන් දෙපය මිරිවැඩි සඟලෙහි පැළඳු", "metaphorical_term": "", "source_domain": "", "target_domain": "", "interpretation": ""}
{"index": {"_index": "metaphoem"}}
{"poem_name": "සිතිවිලි සයුර", "poet": "වීරසිංහ මල්ලිමාරච්චි", "year": "1993", "poem_line": "මහපින් කඳකි! රජ මහ වෙහෙරකි සමිඳු ", "metaphorical_term": "රජ මහ වෙහෙරකි සමිඳු", "source_domain": "හාමුදුරුවෝ", "target_domain": "රජමහ වෙහෙර", "interpretation": "ස්වාමීන් වහන්සේට තිබෙන ගෞරවය මෙයින් විදහා දැක්වේ"}
{"index": {"_index": "metaphoem"}}
{"poem_name": "සිංහල දළදා වංශය", "poet": "අකුරැටියේ අමරවංශ හිමි", "year": "1995", "poem_line": "දැක ඔලමොළ ගිජිඳකු පත් ලෙන් දොරට", "metaphorical_term": "", "source_domain": "", "target_domain": "", "interpretation": ""}
{"index": {"_index": "metaphoem"}}
{"poem_name": "සිංහල දළදා වංශය", "poet": "අකුරැටියේ අමරවංශ හිමි", "year": "1995", "poem_line": "එකසර කෙසර එදු පඬුරද බලැතිට", "metaphorical_term": "", "source_domain": "", "target_domain": "", "interpretation": ""}
{"index": {"_index": "metaphoem"}}
{"poem_name": "සිංහල දළදා වංශය", "poet": "අකුරැටියේ අමරවංශ හිමි", "year": "1995", "poem_line": "ගෙන බල සෙනඟ රුපු සැඩ පහරසෙ මඩනට", "metaphorical_term": "බල සෙනඟ රුපු සැඩපහර සේ", "source_domain": "හමුදාව", "target_domain": "සැඩපහර", "interpretation": "බල හමුදාවේ ශක්තිය මෙයින් පෙනේ"}
{"index": {"_index": "metaphoem"}}
{"poem_name": "සිංහල දළදා වංශය", "poet": "අකුරැටියේ අමරවංශ හිමි", "year": "1995", "poem_line": "නොබියව යුද වැදුනි නුවරින් විත් පිටට", "metaphorical_term": "", "source_domain": "", "target_domain": "", "interpretation": ""}
{"index": {"_index": "metaphoem"}}
{"poem_name": "සිංහල දළදා වංශය", "poet": "අකුරැටියේ අමරවංශ හිමි", "year": "1995", "poem_line": "ගුන රුවනින් ලකළ කුමරිඳු නරවරණ", "metaphorical_term": "", "source_domain": "", "target_domain": "", "interpretation": ""}
{"index": {"_index": "metaphoem"}}
{"poem_name": "සිංහල දළදා වංශය", "poet": "අකුරැටියේ අමරවංශ හිමි", "year": "1995", "poem_line": "වෙසෙසින් පහන් කරවා තම වෙත බැතින", "metaphorical_term": "", "source_domain": "", "target_domain": "", "interpretation": ""}
{"index": {"_index": "metaphoem"}}
{"poem_name": "සිංහල දළදා වංශය", "poet": "අකුරැටියේ අමරවංශ හිමි", "year": "1995", "poem_line": "දළදා හිමිඳු සකසා වඳිමින් නිතින", "metaphorical_term": "", "source_domain": "", "target_domain": "", "interpretation": ""}
{"index": {"_index": "metaphoem"}}
{"poem_name": "සිංහල දළදා වංශය", "poet": "අකුරැටියේ අමරවංශ හිමි", "year": "1995", "poem_line": "රැඳුනා රජ මැදුර මිණි පහනෙව් දිලෙන ", "metaphorical_term": "රජමැදුර මිණි පහනෙව්", "source_domain": "රජ මැදුර", "target_domain": "මිණි පහන", "interpretation": "රජ මැදුරෙහි ශ්‍රී විභූතිය, එහි අනර්ඝත්වය පෙන්වයි"}
{"index": {"_index": "metaphoem"}}
{"poem_name": "සිංහල දළදා වංශය", "poet": "අකුරැටියේ අමරවංශ හිමි", "year": "1995", "poem_line": "කලල් මත සසොබා", "metaphorical_term": "", "source_domain": "", "target_domain": "", "interpretation": ""}
{"index": {"_index": "metaphoem"}}
{"poem_name": "සිංහල දළදා වංශය", "poet": "අකුරැටියේ අමරවංශ හිමි", "year": "1995", "poem_line": "පාපියුම් ඔබ නොතබා", "metaphorical_term": "පා පියුම්", "source_domain": "පාද", "target_domain": "පියුම්", "interpretation": "පාද වල තිබෙන සියුමැලි බව මෙයින් කියවේ"}
{"index": {"_index": "metaphoem"}}
{"poem_name": "සිංහල දළදා වංශය", "poet": "අකුරැටියේ අමරවංශ හිමි", "year": "1995", "poem_line": "පිට මැඩගෙන නොබා", "metaphorical_term": "", "source_domain": "", "target_domain": "", "interpretation": ""}
{"index": {"_index": "metaphoem"}}
{"poem_name": "සිංහල දළදා වංශය", "poet": "අකුරැටියේ අමරවංශ හිමි", "year": "1995", "poem_line": "වඩිනු මැනවැයි කියා මහබා", "metaphorical_term": "", "source_domain": "", "target_domain": "", "interpretation": ""}
{"index": {"_index": "metaphoem"}}
{"poem_name": "හඳක එළිය", "poet": "සිරිමෙවන් ඇහැළේපොළ", "year": "1995", "poem_line": "පෙම්ලොව මැණික් සඳ පායා බබලන්නේ ", "metaphorical_term": "මැණික් සඳ", "source_domain": "සඳ", "target_domain": "මැණික", "interpretation": "සඳෙහි ආලෝකය, කාන්තිය, වටිනාකම පෙන්වයි"}
{"index": {"_index": "metaphoem"}}
{"poem_name": "හඳක එළිය", "poet": "සිරිමෙවන් ඇහැළේපොළ", "year": "1995", "poem_line": "සම්පත රන් එළිය රජ මැදුරට දෙන්නේ", "metaphorical_term": "", "source_domain": "", "target_domain": "", "interpretation": ""}
{"index": {"_index": "metaphoem"}}
{"poem_name": "හඳක එළිය", "poet": "සිරිමෙවන් ඇහැළේපොළ", "year": "1995", "poem_line": "අම්මට තුරුලු වී රන් පුතු කිරි බොන්නේ", "metaphorical_term": "", "source_domain": "", "target_domain": "", "interpretation": ""}
{"index": {"_index": "metaphoem"}}
{"poem_name": "හඳක එළිය", "poet": "සිරිමෙවන් ඇහැළේපොළ", "year": "1995", "poem_line": "සංසාරයේ මරහඬ සවනත වෙන්නේ", "metaphorical_term": "", "source_domain": "", "target_domain": "", "interpretation": ""}
{"index": {"_index": "metaphoem"}}
{"poem_name": "හඳක එළිය", "poet": "සිරිමෙවන් ඇහැළේපොළ", "year": "1995", "poem_line": "දහවල හිරුගෙන් දැලි කුණු ගෑවුණු", "metaphorical_term": "", "source_domain": "", "target_domain": "", "interpretation": ""}
{"index": {"_index": "metaphoem"}}
{"poem_name": "හඳක එළිය", "poet": "සිරිමෙවන් ඇහැළේපොළ", "year": "1995", "poem_line": "රෙදි පිළි ගලවාද බිම තැන තැන", "metaphorical_term": "", "source_domain": "", "target_domain": "", "interpretation": ""}
{"index": {"_index": "metaphoem"}}
{"poem_name": "හඳක එළිය", "poet": "සිරිමෙවන් ඇහැළේපොළ", "year": "1995", "poem_line": "සුදු සඳ රැස් දිය ඇල්ලෙන් නාගෙන ", "metaphorical_term": "සුදු සඳරැස් දිය ඇල්ලෙන්", "source_domain": "සඳ එලිය", "target_domain": "දිය ඇල්ල", "interpretation": "සඳ එලිය හාත් පස පැතිරී ඇති ආකාරය දැක්වෙයි"}
{"index": {"_index": "metaphoem"}}
{"poem_name": "හඳක එළිය", "poet": "සිරිමෙවන් ඇහැළේපොළ", "year": "1995", "poem_line": "නිසන්සලේ ඈත තුරුලිය සිල් ගෙන", "metaphorical_term": "", "source_domain": "", "target_domain": "", "interpretation": ""}
{"index": {"_index": "metaphoem"}}
{"poem_name": "හඳක එළිය", "poet": "සිරිමෙවන් ඇහැළේපොළ", "year": "1995", "poem_line": "උගත්කමේ සිපිරිගෙයින් ", "metaphorical_term": "උගත්කමේ සිපිරි ගෙයින්", "source_domain": "උගත්කම", "target_domain": "සිපිරිගෙය", "interpretation": "මෙහිදී උගත්කම නිසා නොහොබිනා දේ කිරීමට නොහැකි වූ බව කියයි"}
{"index": {"_index": "metaphoem"}}
{"poem_name": "හඳක එළිය", "poet": "සිරිමෙවන් ඇහැළේපොළ", "year": "1995", "poem_line": "මිදී මසිත සඳ එළියේ", "metaphorical_term": "", "source_domain": "", "target_domain": "", "interpretation": ""}
{"index": {"_index": "metaphoem"}}
{"poem_name": "හඳක එළිය", "poet": "සිරිමෙවන් ඇහැළේපොළ", "year": "1995", "poem_line": "පොත් පත් පවුරට ඉහළින්", "metaphorical_term": "", "source_domain": "", "target_domain": "", "interpretation": ""}
{"index": {"_index": "metaphoem"}}
{"poem_name": "හඳක එළිය", "poet": "සිරිමෙවන් ඇහැළේපොළ", "year": "1995", "poem_line": "නික්මෙයි ගමනකට සොඳුරු", "metaphorical_term": "", "source_domain": "", "target_domain": "", "interpretation": ""}
{"index": {"_index": "metaphoem"}}
{"poem_name": "හඳක එළිය", "poet": "සිරිමෙවන් ඇහැළේපොළ", "year": "1995", "poem_line": "මගේ තනිකමේ කෙම්බිම සරු ගහකොළය", "metaphorical_term": "", "source_domain": "", "target_domain": "", "interpretation": ""}
{"index": {"_index": "metaphoem"}}
{"poem_name": "හඳක එළිය", "poet": "සිරිමෙවන් ඇහැළේපොළ", "year": "1995", "poem_line": "කඳුළුය පළිඟු මිණිවන් සිහිලල ජලය", "metaphorical_term": "පළිඟු මිණිවන් සිහිලල ජලය", "source_domain": "ජලය", "target_domain": "පළිඟු මිණි", "interpretation": "ජලයේ ඇති පිරිසිඳු බව, වටිනාකම මෙයින් දැක්වේ"}
{"index": {"_index": "metaphoem"}}
{"poem_name": "හඳක එළිය", "poet": "සිරිමෙවන් ඇහැළේපොළ", "year": "1995", "poem_line": "හැමදා පුර සඳුය දිදුලය නිසසලය", "metaphorical_term": "", "source_domain": "", "target_domain": "", "interpretation": ""}
{"index": {"_index": "metaphoem"}}
{"poem_name": "හඳක එළිය", "poet": "සිරිමෙවන් ඇහැළේපොළ", "year": "1995", "poem_line": "එහි දොර කඩුලු විවටය රසමල් පලය", "metaphorical_term": "", "source_domain": "", "target_domain": "", "interpretation": ""}
{"index": {"_index": "metaphoem"}}
{"poem_name": "හඳක එළිය", "poet": "සිරිමෙවන් ඇහැළේපොළ", "year": "1995", "poem_line": "බැතිබර උවැසියන් ඇසිපිය සලන මෙනී", "metaphorical_term": "", "source_domain": "", "target_domain": "", "interpretation": ""}
{"index": {"_index": "metaphoem"}}
{"poem_name": "හඳක එළිය", "poet": "සිරිමෙවන් ඇහැළේපොළ", "year": "1995", "poem_line": "බෝපත් සැලී සඳ පානින් දිහුල ගනී", "metaphorical_term": "", "source_domain": "", "target_domain": "", "interpretation": ""}
{"index": {"_index": "metaphoem"}}
{"poem_name": "හඳක එළිය", "poet": "සිරිමෙවන් ඇහැළේපොළ", "year": "1995", "poem_line": "වන මැද විහාරය මට කෙම්බිමක වැනී ", "metaphorical_term": "විහාරය මට කෙම්බිමක වැනි", "source_domain": "විහාරය", "target_domain": "කෙම්භූමිය", "interpretation": "කාන්තාරයේ ගමන් ගන්නා විට කෙම්බිමක් හමුවූවා මෙනි විහාරයේ අගය"}
{"index": {"_index": "metaphoem"}}
{"poem_name": "හඳක එළිය", "poet": "සිරිමෙවන් ඇහැළේපොළ", "year": "1995", "poem_line": "ගැමි පිරිසකගෙ 'නූගත්කම' සුවය විණි", "metaphorical_term": "", "source_domain": "", "target_domain": "", "interpretation": ""}
{"index": {"_index": "metaphoem"}}
{"poem_name": "අන්ධ කවියා", "poet": "පී.බී. අල්විස් පෙරේරා", "year": "1944", "poem_line": "සිරුරේ දාහය සනසන නලවැල් සිසිලස ගත් බව දනිමි වැවේ", "metaphorical_term": "නල වැල්", "source_domain": "නල", "target_domain": "වැල්", "interpretation": "වැල් මෙන් එති එතී යන සුළඟේ සිසිල මින් දැක්වේ"}
{"index": {"_index": "metaphoem"}}
{"poem_name": "අන්ධ කවියා", "poet": "පී.බී. අල්විස් පෙරේරා", "year": "1944", "poem_line": "රත්සර හෙළැ'ඹුලු නිලුපුල් මීගඳ නැහැ පුඩු අතරින් ළයට කැවේ", "metaphorical_term": "", "source_domain": "", "target_domain": "", "interpretation": ""}
{"index": {"_index": "metaphoem"}}
{"poem_name": "අන්ධ කවියා", "poet": "පී.බී. අල්විස් පෙරේරා", "year": "1944", "poem_line": "මායා සිහිනය මැද්දේ පිහිනමි එනමුදු නොදකිමි එළිය ලොවේ", "metaphorical_term": "", "source_domain": "", "target_domain": "", "interpretation": ""}
{"index": {"_index": "metaphoem"}}
{"poem_name": "අන්ධ කවියා", "poet": "පී.බී. අල්විස් පෙරේරා", "year": "1944", "poem_line": "හදවත කොඳුරයි එහි සටහන් ළඟ හිඳ පිටපත් කළ හැකිද දුවේ", "metaphorical_term": "", "source_domain": "", "target_domain": "", "interpretation": ""}
{"index": {"_index": "metaphoem"}}
{"poem_name": "අන්ධ කවියා", "poet": "පී.බී. අල්විස් පෙරේරා", "year": "1944", "poem_line": "වැව් බන්දේසිය සොබා සොඳුරි වෙත පිළිගන්වන විට ඇඹුල තබා", "metaphorical_term": "වැව් බන්දේසිය", "source_domain": "වැව", "target_domain": "බන්දේසිය", "interpretation": "වැවේ ස්වරූපය තලයක් මෙන් දිස්වන ආකාරය"}
{"index": {"_index": "metaphoem"}}
{"poem_name": "අන්ධ කවියා", "poet": "පී.බී. අල්විස් පෙරේරා", "year": "1944", "poem_line": "පෙර මෙන් අහසේ පායන රන්හිරු වහුරන්නෙද මිණි කිරණ පබා", "metaphorical_term": "", "source_domain": "", "target_domain": "", "interpretation": ""}
{"index": {"_index": "metaphoem"}}
{"poem_name": "අන්ධ කවියා", "poet": "පී.බී. අල්විස් පෙරේරා", "year": "1944", "poem_line": "වදුලේ පරඬැල් අතුඉළ කැදැල්ලේ තනියම පසුවන කුරුලු බබා", "metaphorical_term": "", "source_domain": "", "target_domain": "", "interpretation": ""}
{"index": {"_index": "metaphoem"}}
{"poem_name": "අන්ධ කවියා", "poet": "පී.බී. අල්විස් පෙරේරා", "year": "1944", "poem_line": "මව නැති අතරේ \"කිචි බිචි\" ගෑවේ ඉගිලෙන පිණිසයි ළඟදි නොබා", "metaphorical_term": "", "source_domain": "", "target_domain": "", "interpretation": ""}
{"index": {"_index": "metaphoem"}}
{"poem_name": "අන්ධ කවියා", "poet": "පී.බී. අල්විස් පෙරේරා", "year": "1944", "poem_line": "ඔබගේ මව සහ මා එක් දවසක් අවර'ඹරෙහි හිරු ගිලෙන පැයේ", "metaphorical_term": "", "source_domain": "", "target_domain": "", "interpretation": ""}
{"index": {"_index": "metaphoem"}}
{"poem_name": "අන්ධ කවියා", "poet": "පී.බී. අල්විස් පෙරේරා", "year": "1944", "poem_line": "හිඳගෙන හුන් විට පුලින තලාවක ඈ විමසූවා වැතිර ළයේ", "metaphorical_term": "", "source_domain": "", "target_domain": "", "interpretation": ""}
{"index": {"_index": "metaphoem"}}
{"poem_name": "අන්ධ කවියා", "poet": "පී.බී. අල්විස් පෙරේරා", "year": "1944", "poem_line": "සැන්දෑ වෙළ පෙති පරයන තොල් ඇති දූ මැණිකක් ඔබ රිසිද පියේ", "metaphorical_term": "දූ මැණිකක්", "source_domain": "දුව", "target_domain": "මැණික", "interpretation": "දුවගේ ඇති අගය, වටිනාකම, සුන්දරත්වය ආදිය පිලිබිඹු කරයි"}
{"index": {"_index": "metaphoem"}}
{"poem_name": "අන්ධ කවියා", "poet": "පී.බී. අල්විස් පෙරේරා", "year": "1944", "poem_line": "ඇය කී වදනෙහි සැබෑව දක්නට පෙර මගෙ නෙත් දෙක නැතිව ගියේ", "metaphorical_term": "", "source_domain": "", "target_domain": "", "interpretation": ""}
